[{"CODPROD":"1","DESCRICAO":"MASSA CORRIDA PVA KOKAR 15KG"},{"CODPROD":"2","DESCRICAO":"MASSA CORRIDA PVA KOKAR 5,5KG"},{"CODPROD":"3","DESCRICAO":"MASSA CORRIDA PVA KOKAR 27KG"},{"CODPROD":"4","DESCRICAO":"MASSA ACRILICA KOKAR 15KG"},{"CODPROD":"5","DESCRICAO":"MASSA ACRILICA KOKAR 5,5KG"},{"CODPROD":"6","DESCRICAO":"MASSA ACRILICA KOKAR 27KG"},{"CODPROD":"7","DESCRICAO":"SELADOR ACRILICO KOKAR 18LT "},{"CODPROD":"8","DESCRICAO":"SELADOR ACRILICO KOKAR 3,6L"},{"CODPROD":"9","DESCRICAO":"FUNDO PREPARADOR DE PAREDES KOKAR 18L"},{"CODPROD":"10","DESCRICAO":"FUNDO PREPARADOR DE PAREDES 3,6L"},{"CODPROD":"11","DESCRICAO":"ECONOMICO FOSCO 18L BRANCO NEVE"},{"CODPROD":"12","DESCRICAO":"STANDARD FS ULTRA 18L BRANCO NEVE"},{"CODPROD":"13","DESCRICAO":"STANDARD FS ULTRA 3,6L BRANCO NEVE"},{"CODPROD":"14","DESCRICAO":"ECONOMICO FOSCO 3,6L BRANCO NEVE"},{"CODPROD":"16","DESCRICAO":"ECONOMICO FOSCO 18L AMARELO CANARIO"},{"CODPROD":"17","DESCRICAO":"ECONOMICO FOSCO 18L AREIA"},{"CODPROD":"18","DESCRICAO":"ECONOMICO FOSCO 18L CAMURCA"},{"CODPROD":"22","DESCRICAO":"ECONOMICO FOSCO 18L BRANCO GELO"},{"CODPROD":"23","DESCRICAO":"ECONOMICO FOSCO 18L PEROLA"},{"CODPROD":"25","DESCRICAO":"ECONOMICO FOSCO 18L ERVA DOCE"},{"CODPROD":"26","DESCRICAO":"ECONOMICO FOSCO 18L VERDE KIWI"},{"CODPROD":"31","DESCRICAO":"ECONOMICO FOSCO 18L PALHA"},{"CODPROD":"35","DESCRICAO":"ECONOMICO FOSCO 18L VERDE LIMAO"},{"CODPROD":"36","DESCRICAO":"ECONOMICO FOSCO 3,6L AMARELO CANARIO"},{"CODPROD":"37","DESCRICAO":"ECONOMICO FOSCO 3,6L AREIA"},{"CODPROD":"38","DESCRICAO":"ECONOMICO FOSCO 3,6L CAMURCA"},{"CODPROD":"42","DESCRICAO":"ECONOMICO FOSCO 3,6L BRANCO GELO"},{"CODPROD":"43","DESCRICAO":"ECONOMICO FOSCO 3,6L PEROLA"},{"CODPROD":"45","DESCRICAO":"ECONOMICO FOSCO 3,6L ERVA DOCE"},{"CODPROD":"46","DESCRICAO":"ECONOMICO FOSCO 3,6L VERDE KIWI"},{"CODPROD":"51","DESCRICAO":"ECONOMICO FOSCO 3,6L PALHA"},{"CODPROD":"55","DESCRICAO":"ECONOMICO FOSCO 3,6L VERDE LIMAO"},{"CODPROD":"57","DESCRICAO":"STANDARD FS ULTRA 18L AREIA"},{"CODPROD":"58","DESCRICAO":"STANDARD FS ULTRA 18L CAMURCA"},{"CODPROD":"60","DESCRICAO":"STANDARD FS ULTRA 18L AZUL PROFUNDO"},{"CODPROD":"62","DESCRICAO":"STANDARD FS ULTRA 18L BRANCO GELO"},{"CODPROD":"63","DESCRICAO":"STANDARD FS ULTRA 18L CAFE COM LEITE"},{"CODPROD":"66","DESCRICAO":"STANDARD FS ULTRA 18L CINZA AVELUDADO"},{"CODPROD":"67","DESCRICAO":"STANDARD FS ULTRA 18L AZUL OCEANO"},{"CODPROD":"72","DESCRICAO":"STANDARD FS ULTRA 18L AMARELO SOL"},{"CODPROD":"74","DESCRICAO":"STANDARD FS ULTRA 18L PALHA"},{"CODPROD":"76","DESCRICAO":"STANDARD FS ULTRA 18L AZUL SERENO"},{"CODPROD":"77","DESCRICAO":"STANDARD FS ULTRA 18L VERDE LIMAO"},{"CODPROD":"79","DESCRICAO":"STANDARD FS ULTRA 3,6L AREIA"},{"CODPROD":"80","DESCRICAO":"STANDARD FS ULTRA 3,6L CAMURCA"},{"CODPROD":"82","DESCRICAO":"STANDARD FS ULTRA 3,6L AZUL PROFUNDO"},{"CODPROD":"84","DESCRICAO":"STANDARD FS ULTRA 3,6L BRANCO GELO"},{"CODPROD":"85","DESCRICAO":"STANDARD FS ULTRA 3,6L CAFE COM LEITE"},{"CODPROD":"88","DESCRICAO":"STANDARD FS ULTRA 3,6L CINZA AVELUDA"},{"CODPROD":"89","DESCRICAO":"STANDARD FS ULTRA 3,6L AZUL OCEANO"},{"CODPROD":"94","DESCRICAO":"STANDARD FS ULTRA 3,6L AMARELO SOL"},{"CODPROD":"96","DESCRICAO":"STANDARD FS ULTRA 3,6L PALHA"},{"CODPROD":"98","DESCRICAO":"STANDARD FS ULTRA 3,6L AZUL SERENO"},{"CODPROD":"100","DESCRICAO":"STANDARD FS ULTRA 3,6L VERDE LIMAO"},{"CODPROD":"101","DESCRICAO":"PREMIUM FOSCO 18L BRANCO NEVE"},{"CODPROD":"102","DESCRICAO":"PREMIUM FOSCO 3,6L BRANCO NEVE"},{"CODPROD":"103","DESCRICAO":"PREMIUM ACET SEDA 18L BRANCO NEVE"},{"CODPROD":"104","DESCRICAO":"PREMIUM ACET SEDA 3,6L BRANCO NEVE"},{"CODPROD":"105","DESCRICAO":"PREMIUM SEMIBRILHO 3,6L BRANCO NEVE"},{"CODPROD":"106","DESCRICAO":"PREMIUM SEMIBRILHO 18L BRANCO NEVE"},{"CODPROD":"107","DESCRICAO":"STANDARD SB 18L BRANCO NEVE"},{"CODPROD":"108","DESCRICAO":"STANDARD SB 3,6L BRANCO NEVE"},{"CODPROD":"110","DESCRICAO":"PREMIUM FOSCO 18L ALGODAO DA TERRA"},{"CODPROD":"111","DESCRICAO":"PREMIUM FOSCO 18L AMARELO CANARIO"},{"CODPROD":"113","DESCRICAO":"PREMIUM FOSCO 18L AREIA"},{"CODPROD":"114","DESCRICAO":"PREMIUM FOSCO 18L CAMURCA"},{"CODPROD":"117","DESCRICAO":"PREMIUM FOSCO 18L BRANCO GELO"},{"CODPROD":"118","DESCRICAO":"PREMIUM FOSCO 18L CHOCOLATE"},{"CODPROD":"119","DESCRICAO":"PREMIUM FOSCO 18L PEROLA"},{"CODPROD":"121","DESCRICAO":"PREMIUM FOSCO 18L VERDE ESPERANCA"},{"CODPROD":"122","DESCRICAO":"PREMIUM FOSCO 18L AZUL OCEANO"},{"CODPROD":"123","DESCRICAO":"PREMIUM FOSCO 18L ERVA DOCE"},{"CODPROD":"124","DESCRICAO":"PREMIUM FOSCO 18L VERDE KIWI"},{"CODPROD":"125","DESCRICAO":"PREMIUM FOSCO 18L LARANJA"},{"CODPROD":"126","DESCRICAO":"PREMIUM FOSCO 18L LILAS"},{"CODPROD":"131","DESCRICAO":"PREMIUM FOSCO 18L PALHA"},{"CODPROD":"133","DESCRICAO":"PREMIUM FOSCO 18L VERDE MUSGO"},{"CODPROD":"134","DESCRICAO":"PREMIUM FOSCO 18L ROXO PAVAO"},{"CODPROD":"135","DESCRICAO":"PREMIUM FOSCO 18L TERRACOTA"},{"CODPROD":"137","DESCRICAO":"PREMIUM FOSCO 18L VERDE LIMAO"},{"CODPROD":"138","DESCRICAO":"PREMIUM FOSCO 3,6L ACAI"},{"CODPROD":"139","DESCRICAO":"PREMIUM FOSCO 3,6L ALGODAO DA TERRA"},{"CODPROD":"140","DESCRICAO":"PREMIUM FOSCO 3,6L AMARELO CANARIO"},{"CODPROD":"142","DESCRICAO":"PREMIUM FOSCO 3,6L AREIA"},{"CODPROD":"143","DESCRICAO":"PREMIUM FOSCO 3,6L CAMURCA"},{"CODPROD":"146","DESCRICAO":"PREMIUM FOSCO 3,6L BRANCO GELO"},{"CODPROD":"147","DESCRICAO":"PREMIUM FOSCO 3,6L CHOCOLATE"},{"CODPROD":"148","DESCRICAO":"PREMIUM FOSCO 3,6L PEROLA"},{"CODPROD":"151","DESCRICAO":"PREMIUM FOSCO 3,6L AZUL OCEANO"},{"CODPROD":"152","DESCRICAO":"PREMIUM FOSCO 3,6L ERVA DOCE"},{"CODPROD":"153","DESCRICAO":"PREMIUM FOSCO 3,6L VERDE KIWI"},{"CODPROD":"154","DESCRICAO":"PREMIUM FOSCO 3,6L VERDE ESPERANCA"},{"CODPROD":"155","DESCRICAO":"PREMIUM FOSCO 3,6L LILAS"},{"CODPROD":"156","DESCRICAO":"PREMIUM FOSCO 3,6L AZUL ARARA"},{"CODPROD":"157","DESCRICAO":"PREMIUM FOSCO 3,6L MARFIM ANTIGO"},{"CODPROD":"159","DESCRICAO":"PREMIUM FOSCO 3,6L VERMELHO ARARA"},{"CODPROD":"160","DESCRICAO":"PREMIUM FOSCO 3,6L PALHA"},{"CODPROD":"162","DESCRICAO":"PREMIUM FOSCO 3,6L VERDE MUSGO"},{"CODPROD":"163","DESCRICAO":"PREMIUM FOSCO 3,6L ROXO PAVAO"},{"CODPROD":"164","DESCRICAO":"PREMIUM FOSCO 3,6L TERRACOTA"},{"CODPROD":"166","DESCRICAO":"PREMIUM FOSCO 3,6L VERDE LIMAO"},{"CODPROD":"167","DESCRICAO":"PREMIUM ACET SEDA 18L ALGODAO DA TERRA"},{"CODPROD":"169","DESCRICAO":"PREMIUM ACET SEDA 18L SEIXO BRANCO"},{"CODPROD":"170","DESCRICAO":"PREMIUM ACET SEDA 18L BRANCO GELO"},{"CODPROD":"171","DESCRICAO":"PREMIUM ACET SEDA 18L PALHA"},{"CODPROD":"172","DESCRICAO":"PREMIUM ACET SEDA 3,6L ALGODAO DA TERRA"},{"CODPROD":"174","DESCRICAO":"PREMIUM ACET SEDA 3,6L SEIXO BRANCO"},{"CODPROD":"175","DESCRICAO":"PREMIUM ACET SEDA 3,6L BRANCO GELO"},{"CODPROD":"176","DESCRICAO":"PREMIUM ACET SEDA 3,6L PALHA"},{"CODPROD":"178","DESCRICAO":"PREMIUM SEMIBRILHO 18L ALGODAO DA TERRA"},{"CODPROD":"179","DESCRICAO":"PREMIUM SEMIBRILHO 18L AREIA"},{"CODPROD":"180","DESCRICAO":"PREMIUM SEMIBRILHO 18L CAMURCA"},{"CODPROD":"184","DESCRICAO":"PREMIUM SEMIBRILHO 18L BRANCO GELO"},{"CODPROD":"186","DESCRICAO":"PREMIUM SEMIBRILHO 18L PEROLA"},{"CODPROD":"187","DESCRICAO":"PREMIUM SEMIBRILHO 18L VERDE KIWI"},{"CODPROD":"188","DESCRICAO":"PREMIUM SEMIBRILHO 18L LARANJA"},{"CODPROD":"189","DESCRICAO":"PREMIUM SEMIBRILHO 18L LILAS"},{"CODPROD":"194","DESCRICAO":"PREMIUM SEMIBRILHO 18L PALHA"},{"CODPROD":"195","DESCRICAO":"PREMIUM SEMIBRILHO 18L VERDE ESPERANCA"},{"CODPROD":"196","DESCRICAO":"PREMIUM SEMIBRILHO 18L VERDE LIMAO"},{"CODPROD":"198","DESCRICAO":"PREMIUM SEMIBRILHO 3,6L ALGODAO DA TERRA"},{"CODPROD":"199","DESCRICAO":"PREMIUM SEMIBRILHO 3,6L AREIA"},{"CODPROD":"200","DESCRICAO":"PREMIUM SEMIBRILHO 3,6L CAMURCA"},{"CODPROD":"204","DESCRICAO":"PREMIUM SEMIBRILHO 3,6L BRANCO GELO"},{"CODPROD":"206","DESCRICAO":"PREMIUM SEMIBRILHO 3,6L PEROLA"},{"CODPROD":"208","DESCRICAO":"PREMIUM SEMIBRILHO 3,6L VERDE KIWI"},{"CODPROD":"209","DESCRICAO":"PREMIUM SEMIBRILHO 3,6L LARANJA"},{"CODPROD":"210","DESCRICAO":"PREMIUM SEMIBRILHO 3,6L LILAS"},{"CODPROD":"215","DESCRICAO":"PREMIUM SEMIBRILHO 3,6L PALHA"},{"CODPROD":"216","DESCRICAO":"PREMIUM SEMIBRILHO 3,6L VERDE ESPERANCA"},{"CODPROD":"217","DESCRICAO":"PREMIUM SEMIBRILHO 3,6L VERDE LIMAO"},{"CODPROD":"218","DESCRICAO":"STANDARD SB 18L AMARELO CANARIO"},{"CODPROD":"220","DESCRICAO":"STANDARD SB 18L AREIA"},{"CODPROD":"221","DESCRICAO":"STANDARD SB 18L CAMURCA"},{"CODPROD":"225","DESCRICAO":"STANDARD SB 18L BRANCO GELO"},{"CODPROD":"226","DESCRICAO":"STANDARD SB 18L PEROLA"},{"CODPROD":"228","DESCRICAO":"STANDARD SB 18L CINZA AVELUDADO"},{"CODPROD":"230","DESCRICAO":"STANDARD SB 18L AZUL OCEANO"},{"CODPROD":"232","DESCRICAO":"STANDARD SB 18L VERDE KIWI"},{"CODPROD":"234","DESCRICAO":"STANDARD SB 18L MARFIM ANTIGO"},{"CODPROD":"235","DESCRICAO":"STANDARD SB 18L AMARELO SOL"},{"CODPROD":"237","DESCRICAO":"STANDARD SB 18L PALHA"},{"CODPROD":"238","DESCRICAO":"STANDARD SB 18L VERDE ESPERANCA"},{"CODPROD":"241","DESCRICAO":"STANDARD SB 18L VERDE LIMAO"},{"CODPROD":"242","DESCRICAO":"STANDARD SB 3,6L AMARELO CANARIO"},{"CODPROD":"243","DESCRICAO":"STANDARD SB 3,6L AREIA"},{"CODPROD":"244","DESCRICAO":"STANDARD SB 3,6L CAMURCA"},{"CODPROD":"248","DESCRICAO":"STANDARD SB 3,6L BRANCO GELO"},{"CODPROD":"249","DESCRICAO":"STANDARD SB 3,6L PEROLA"},{"CODPROD":"251","DESCRICAO":"STANDARD SB 3,6L CINZA AVELUDA"},{"CODPROD":"252","DESCRICAO":"STANDARD SB 3,6L AZUL OCEANO"},{"CODPROD":"254","DESCRICAO":"STANDARD SB 3,6L VERDE KIWI"},{"CODPROD":"257","DESCRICAO":"STANDARD SB 3,6L AMARELO SOL"},{"CODPROD":"259","DESCRICAO":"STANDARD SB 3,6L PALHA"},{"CODPROD":"260","DESCRICAO":"STANDARD SB 3,6L VERDE ESPERANCA"},{"CODPROD":"262","DESCRICAO":"STANDARD SB 3,6L ROSA CHA"},{"CODPROD":"263","DESCRICAO":"STANDARD SB 3,6L VERDE LIMAO"},{"CODPROD":"269","DESCRICAO":"RESINA ACR BA KOKAR 18L CERAMICA ONIX"},{"CODPROD":"270","DESCRICAO":"RESINA ACR BA KOKAR 18L CERAMICA TELHA"},{"CODPROD":"271","DESCRICAO":"RESINA ACR BA KOKAR 18L CINZA"},{"CODPROD":"272","DESCRICAO":"RESINA ACR BA KOKAR 18L CONCRETO"},{"CODPROD":"273","DESCRICAO":"RESINA ACR BA KOKAR 18L INCOLOR"},{"CODPROD":"274","DESCRICAO":"RESINA ACR BA KOKAR 18L VERMELHO OXIDO"},{"CODPROD":"275","DESCRICAO":"RESINA ACR BA KOKAR 3,6L BRANCO NEVE"},{"CODPROD":"276","DESCRICAO":"RESINA ACR BA KOKAR 3,6L CERAMICA ONIX"},{"CODPROD":"277","DESCRICAO":"RESINA ACR BA KOKAR 3,6L CERAMICA TELHA"},{"CODPROD":"278","DESCRICAO":"RESINA ACR BA KOKAR 3,6L CINZA"},{"CODPROD":"279","DESCRICAO":"RESINA ACR BA KOKAR 3,6L CONCRETO"},{"CODPROD":"280","DESCRICAO":"RESINA ACR BA KOKAR 3,6L INCOLOR"},{"CODPROD":"281","DESCRICAO":"RESINA ACR BA KOKAR 3,6L VERMELHO OXIDO"},{"CODPROD":"375","DESCRICAO":"PISO PREMIUM FS 18L AMARELO DEMARCACAO"},{"CODPROD":"376","DESCRICAO":"PISO PREMIUM FS 18L AZUL"},{"CODPROD":"377","DESCRICAO":"PISO PREMIUM FS 18L BRANCO NEVE"},{"CODPROD":"378","DESCRICAO":"PISO PREMIUM FS 18L CINZA"},{"CODPROD":"379","DESCRICAO":"PISO PREMIUM FS 18L CONCRETO"},{"CODPROD":"381","DESCRICAO":"PISO PREMIUM FS 18L LARANJA"},{"CODPROD":"382","DESCRICAO":"PISO PREMIUM FS 18L PRETO"},{"CODPROD":"383","DESCRICAO":"PISO PREMIUM FS 18L VERDE QUADRA"},{"CODPROD":"386","DESCRICAO":"PISO PREMIUM FS 3,6L AMARELO DEMARCACA"},{"CODPROD":"388","DESCRICAO":"PISO PREMIUM FS 3,6L AZUL"},{"CODPROD":"389","DESCRICAO":"PISO PREMIUM FS 3,6L BRANCO NEVE"},{"CODPROD":"390","DESCRICAO":"PISO PREMIUM FS 3,6L CINZA"},{"CODPROD":"391","DESCRICAO":"PISO PREMIUM FS 3,6L CONCRETO"},{"CODPROD":"393","DESCRICAO":"PISO PREMIUM FS 3,6L LARANJA"},{"CODPROD":"394","DESCRICAO":"PISO PREMIUM FS 3,6L PRETO"},{"CODPROD":"395","DESCRICAO":"PISO PREMIUM FS 3,6L VERDE QUADRA"},{"CODPROD":"491","DESCRICAO":"RESINA ACR BA KOKAR 18L BRANCO NEVE"},{"CODPROD":"754","DESCRICAO":"GESSO & DRYWALL KOKAR 18L BRANCO NEVE "},{"CODPROD":"755","DESCRICAO":"GESSO & DRYWALL KOKAR 3,6L BRANCO NEVE "},{"CODPROD":"783","DESCRICAO":"TEXTURA TRADICIONAL 25KG AMARELO CANARIO"},{"CODPROD":"834","DESCRICAO":"STANDARD FS ULTRA 18L CHOCOLATE"},{"CODPROD":"836","DESCRICAO":"STANDARD FS ULTRA 3,6L CHOCOLATE"},{"CODPROD":"837","DESCRICAO":"STANDARD SB 18L LILAS"},{"CODPROD":"838","DESCRICAO":"STANDARD SB 18L CHOCOLATE"},{"CODPROD":"839","DESCRICAO":"STANDARD SB 3,6L LILAS"},{"CODPROD":"840","DESCRICAO":"STANDARD SB 3,6L CHOCOLATE"},{"CODPROD":"842","DESCRICAO":"PREMIUM FOSCO 18L CAFE COM LEITE"},{"CODPROD":"843","DESCRICAO":"PREMIUM FOSCO 3,6L CAFE COM LEITE"},{"CODPROD":"969","DESCRICAO":"MASSA CORRIDA PVA KOKAR 20KG"},{"CODPROD":"981","DESCRICAO":"FIT ACR FS ECONOMICO 16L BRANCO NEVE "},{"CODPROD":"990","DESCRICAO":"FIT ACR FS ECONOMICO 16L BRANCO GELO"},{"CODPROD":"991","DESCRICAO":"FIT ACR FS ECONOMICO 16L PALHA"},{"CODPROD":"992","DESCRICAO":"FIT ACR FS ECONOMICO 16L PEROLA"},{"CODPROD":"997","DESCRICAO":"FIT ACR FS ECONOMICO 16L AMARELO CANARIO"},{"CODPROD":"999","DESCRICAO":"FIT MASSA CORRIDA PVA 25KG"},{"CODPROD":"1002","DESCRICAO":"FIT MASSA ACRILICA 25KG"},{"CODPROD":"1003","DESCRICAO":"FIT MASSA CORRIDA PVA 5,5KG"},{"CODPROD":"1004","DESCRICAO":"FIT MASSA ACRILICA 5,5KG"},{"CODPROD":"1008","DESCRICAO":"FIT SELADOR ACRILICO KOKAR 16L"},{"CODPROD":"1009","DESCRICAO":"FIT SELADOR ACRILICO 3,6L"},{"CODPROD":"1010","DESCRICAO":"MASSA ACRILICA KOKAR 20KG"},{"CODPROD":"1011","DESCRICAO":"FIT ACR FS ECONOMICO 3,6L BRANCO NEVE"},{"CODPROD":"1012","DESCRICAO":"FIT ACR FS ECONOMICO 3,6L BRANCO GELO"},{"CODPROD":"1013","DESCRICAO":"FIT ACR FS ECONOMICO 3,6L PALHA"},{"CODPROD":"1014","DESCRICAO":"FIT ACR FS ECONOMICO 3,6L PEROLA"},{"CODPROD":"1019","DESCRICAO":"FIT ACR FS ECONOMICO 3,6L AMARELO CANAR"},{"CODPROD":"1027","DESCRICAO":"PREMIUM FOSCO 18L AMARELO REAL"},{"CODPROD":"1028","DESCRICAO":"PREMIUM FOSCO 3,6L AMARELO REAL"},{"CODPROD":"1031","DESCRICAO":"STANDARD FS ULTRA 18L TITANIO"},{"CODPROD":"1032","DESCRICAO":"STANDARD FS ULTRA 3,6L TITANIO"},{"CODPROD":"1055","DESCRICAO":"PISO PREMIUM FS 18L VERMELHO SEGURANCA"},{"CODPROD":"1056","DESCRICAO":"PISO PREMIUM FS 3,6L VERMELHO SEGURANCA"},{"CODPROD":"1067","DESCRICAO":"TEXTURA RISCADA 25KG BRANCO GELO"},{"CODPROD":"1068","DESCRICAO":"TEXTURA RISCADA 25KG BRANCO NATURAL"},{"CODPROD":"1070","DESCRICAO":"TEXTURA RISCADA 25KG PALHA"},{"CODPROD":"1077","DESCRICAO":"TEXTURA TRADICIONAL 25KG BRANCO GELO"},{"CODPROD":"1078","DESCRICAO":"TEXTURA TRADICIONAL 25KG BRANCO NATURAL"},{"CODPROD":"1080","DESCRICAO":"TEXTURA TRADICIONAL 25KG PALHA"},{"CODPROD":"1135","DESCRICAO":"FIT FUNDO PREPARADOR DE PAREDES 16L"},{"CODPROD":"1136","DESCRICAO":"FIT FUNDO PREPARADOR DE PAREDES 3,6L"},{"CODPROD":"1164","DESCRICAO":"STANDARD FS ULTRA 18L VERDE MUSGO"},{"CODPROD":"1166","DESCRICAO":"STANDARD FS ULTRA 3,6L VERDE MUSGO"},{"CODPROD":"1168","DESCRICAO":"STANDARD FS ULTRA 3,6L AMARELO REAL"},{"CODPROD":"1169","DESCRICAO":"STANDARD FS ULTRA 18L AMARELO REAL"},{"CODPROD":"1171","DESCRICAO":"PREMIUM ACET SEDA 3,6L AREIA"},{"CODPROD":"1172","DESCRICAO":"PREMIUM ACET SEDA 18L AREIA"},{"CODPROD":"1177","DESCRICAO":"STANDARD SB 18L VERMELHO PAIXAO"},{"CODPROD":"1180","DESCRICAO":"STANDARD SB 18L VERDE MUSGO"},{"CODPROD":"1181","DESCRICAO":"STANDARD SB 3,6L VERDE MUSGO"},{"CODPROD":"1183","DESCRICAO":"STANDARD SB 18L AMARELO REAL"},{"CODPROD":"1184","DESCRICAO":"STANDARD SB 3,6L AMARELO REAL"},{"CODPROD":"1186","DESCRICAO":"STANDARD SB 18L CAFE COM LEITE"},{"CODPROD":"1187","DESCRICAO":"STANDARD SB 3,6L CAFE COM LEITE"},{"CODPROD":"1192","DESCRICAO":"PREMIUM FOSCO 18L CONCRETO"},{"CODPROD":"1193","DESCRICAO":"PREMIUM FOSCO 3,6L CONCRETO"},{"CODPROD":"1195","DESCRICAO":"PREMIUM SEMIBRILHO 18L CONCRETO"},{"CODPROD":"1196","DESCRICAO":"PREMIUM SEMIBRILHO 3,6L CONCRETO"},{"CODPROD":"1202","DESCRICAO":"RESINA ACR BA KOKAR 18L PEROLA"},{"CODPROD":"1203","DESCRICAO":"RESINA ACR BA KOKAR 3,6L PEROLA"},{"CODPROD":"1230","DESCRICAO":"PREMIUM SEMIBRILHO 18L AMARELO CANARIO"},{"CODPROD":"1231","DESCRICAO":"PREMIUM SEMIBRILHO 3,6L AMARELO CANARIO"},{"CODPROD":"1233","DESCRICAO":"PREMIUM SEMIBRILHO 18L AMARELO REAL"},{"CODPROD":"1234","DESCRICAO":"PREMIUM SEMIBRILHO 3,6L AMARELO REAL"},{"CODPROD":"1239","DESCRICAO":"PREMIUM SEMIBRILHO 18L AZUL OCEANO"},{"CODPROD":"1240","DESCRICAO":"PREMIUM SEMIBRILHO 3,6L AZUL OCEANO"},{"CODPROD":"1242","DESCRICAO":"PREMIUM SEMIBRILHO 18L CAFE COM LEITE"},{"CODPROD":"1243","DESCRICAO":"PREMIUM SEMIBRILHO 3,6L CAFE COM LEITE"},{"CODPROD":"1245","DESCRICAO":"PREMIUM SEMIBRILHO 18L CHOCOLATE"},{"CODPROD":"1246","DESCRICAO":"PREMIUM SEMIBRILHO 3,6L CHOCOLATE"},{"CODPROD":"1251","DESCRICAO":"PREMIUM SEMIBRILHO 18L ROXO PAVAO"},{"CODPROD":"1252","DESCRICAO":"PREMIUM SEMIBRILHO 3,6L ROXO PAVAO"},{"CODPROD":"1255","DESCRICAO":"PREMIUM SEMIBRILHO 18L VERDE MUSGO"},{"CODPROD":"1256","DESCRICAO":"PREMIUM SEMIBRILHO 3,6L VERDE MUSGO"},{"CODPROD":"1263","DESCRICAO":"TEXTURA TRADICIONAL 15KG BRANCO NATURAL"},{"CODPROD":"1264","DESCRICAO":"TEXTURA RISCADA 15KG BRANCO NATURAL"},{"CODPROD":"1315","DESCRICAO":"TEXTURA TRADICIONAL 15KG BRANCO GELO"},{"CODPROD":"1321","DESCRICAO":"TEXTURA RISCADA 15KG FLORESTA DO SUL"},{"CODPROD":"1348","DESCRICAO":"TEXTURA TRADICIONAL 25KG CONCRETO"},{"CODPROD":"1393","DESCRICAO":"TEXTURA RISCADA 25KG FLORESTA DO SUL"},{"CODPROD":"1406","DESCRICAO":"FIT SELADOR ACRILICO KOKAR 16L CONCRETO"},{"CODPROD":"1415","DESCRICAO":"FIT ACR FS ECONOMICO 16L AREIA"},{"CODPROD":"1441","DESCRICAO":"STANDARD FS ULTRA 18L CINZA PRATEADO"},{"CODPROD":"1566","DESCRICAO":"ESMALTE SINT BRILHANTE 3,6L AMARELO OURO"},{"CODPROD":"1567","DESCRICAO":"ESMALTE SINT BRILHANTE 3,6L AMARELO TRAT"},{"CODPROD":"1568","DESCRICAO":"ESMALTE SINT BRILHANTE 3,6L AREIA"},{"CODPROD":"1569","DESCRICAO":"ESMALTE SINT BRILHANTE 3,6L AZUL CELESTE"},{"CODPROD":"1570","DESCRICAO":"ESMALTE SINT BRILHANTE 3,6L AZUL DEL REY"},{"CODPROD":"1571","DESCRICAO":"ESMALTE SINT BRILHANTE 3,6L AZUL FRANCA"},{"CODPROD":"1572","DESCRICAO":"ESMALTE SINT BRILHANTE 3,6L BRANCO GELO"},{"CODPROD":"1573","DESCRICAO":"ESMALTE SINT BRILHANTE 3,6L BRANCO NEVE"},{"CODPROD":"1574","DESCRICAO":"ESMALTE SINT BRILHANTE 3,6L CAMURCA"},{"CODPROD":"1575","DESCRICAO":"ESMALTE SINT BRILHANTE 3,6L CINZA ESCURO"},{"CODPROD":"1576","DESCRICAO":"ESMALTE SINT BRILHANTE 3,6L CINZA MEDIO"},{"CODPROD":"1577","DESCRICAO":"ESMALTE SINT BRILHANTE 3,6L COLORADO"},{"CODPROD":"1578","DESCRICAO":"ESMALTE SINT BRILHANTE 3,6L CONHAQUE"},{"CODPROD":"1579","DESCRICAO":"ESMALTE SINT BRILHANTE 3,6L LARANJA"},{"CODPROD":"1580","DESCRICAO":"ESMALTE SINT BRILHANTE 3,6L MARFIM"},{"CODPROD":"1581","DESCRICAO":"ESMALTE SINT BRILHANTE 3,6L MARROM"},{"CODPROD":"1582","DESCRICAO":"ESMALTE SINT BRILHANTE 3,6L PALHA"},{"CODPROD":"1583","DESCRICAO":"ESMALTE SINT BRILHANTE 3,6L PLATINA"},{"CODPROD":"1584","DESCRICAO":"ESMALTE SINT BRILHANTE 3,6L PRETO"},{"CODPROD":"1585","DESCRICAO":"ESMALTE SINT BRILHANTE 3,6L TABACO"},{"CODPROD":"1586","DESCRICAO":"ESMALTE SINT BRILHANTE 3,6L VENTO NATUR"},{"CODPROD":"1587","DESCRICAO":"ESMALTE SINT BRILHANTE 3,6L VERDE AMAZON"},{"CODPROD":"1588","DESCRICAO":"ESMALTE SINT BRILHANTE 3,6L VERDE COLONI"},{"CODPROD":"1589","DESCRICAO":"ESMALTE SINT BRILHANTE 3,6L VERDE FOLHA"},{"CODPROD":"1590","DESCRICAO":"ESMALTE SINT BRILHANTE 3,6L VERMELHO"},{"CODPROD":"1591","DESCRICAO":"ESMALTE SINT BRILHANTE 3,6L VERMELHO GOY"},{"CODPROD":"1592","DESCRICAO":"ESMALTE SINT BRILHANTE 0,9L AMAR. OURO"},{"CODPROD":"1593","DESCRICAO":"ESMALTE SINT BRILHANTE 0,9L AMAR. TRATOR"},{"CODPROD":"1594","DESCRICAO":"ESMALTE SINT BRILHANTE 0,9L AREIA"},{"CODPROD":"1598","DESCRICAO":"ESMALTE SINT BRILHANTE 0,9L BRANCO GELO"},{"CODPROD":"1599","DESCRICAO":"ESMALTE SINT BRILHANTE 0,9L AZUL CELESTE"},{"CODPROD":"1600","DESCRICAO":"ESMALTE SINT BRILHANTE 0,9L AZUL DEL REY"},{"CODPROD":"1601","DESCRICAO":"ESMALTE SINT BRILHANTE 0,9L AZUL FRANCA"},{"CODPROD":"1602","DESCRICAO":"ESMALTE SINT BRILHANTE 0,9L CAMURCA"},{"CODPROD":"1603","DESCRICAO":"ESMALTE SINT BRILHANTE 0,9L CINZA MEDIO"},{"CODPROD":"1604","DESCRICAO":"ESMALTE SINT BRILHANTE 0,9L CINZA ESCURO"},{"CODPROD":"1605","DESCRICAO":"ESMALTE SINT BRILHANTE 0,9L COLORADO"},{"CODPROD":"1606","DESCRICAO":"ESMALTE SINT BRILHANTE 0,9L CONHAQUE"},{"CODPROD":"1607","DESCRICAO":"ESMALTE SINT BRILHANTE 0,9L LARANJA"},{"CODPROD":"1608","DESCRICAO":"ESMALTE SINT BRILHANTE 0,9L MARFIM"},{"CODPROD":"1609","DESCRICAO":"ESMALTE SINT BRILHANTE 0,9L MARROM"},{"CODPROD":"1610","DESCRICAO":"ESMALTE SINT BRILHANTE 0,9L PALHA"},{"CODPROD":"1611","DESCRICAO":"ESMALTE SINT BRILHANTE 0,9L PLATINA"},{"CODPROD":"1612","DESCRICAO":"ESMALTE SINT BRILHANTE 0,9L PRETO"},{"CODPROD":"1613","DESCRICAO":"ESMALTE SINT BRILHANTE 0,9L TABACO"},{"CODPROD":"1614","DESCRICAO":"ESMALTE SINT BRILHANTE 0,9L VENTO NATUR."},{"CODPROD":"1615","DESCRICAO":"ESMALTE SINT BRILHANTE 0,9L VERDE AMAZ."},{"CODPROD":"1616","DESCRICAO":"ESMALTE SINT BRILHANTE 0,9L VERDE COLON."},{"CODPROD":"1617","DESCRICAO":"ESMALTE SINT BRILHANTE 0,9L VERDE FOLHA"},{"CODPROD":"1618","DESCRICAO":"ESMALTE SINT BRILHANTE 0,9L VERMELHO"},{"CODPROD":"1619","DESCRICAO":"ESMALTE SINT BRILHANTE 0,9L VERM. GOYA"},{"CODPROD":"1620","DESCRICAO":"ESMALTE SINT FOSCO 3,6L BRANCO NEVE"},{"CODPROD":"1621","DESCRICAO":"ESMALTE SINT FOSCO 3,6L PRETO"},{"CODPROD":"1622","DESCRICAO":"ESMALTE SINT FOSCO 0,9L BRANCO NEVE"},{"CODPROD":"1623","DESCRICAO":"ESMALTE SINT FOSCO 0,9L PRETO"},{"CODPROD":"1624","DESCRICAO":"FUNDO SINTETICO 3,6L CINZA MEDIO"},{"CODPROD":"1625","DESCRICAO":"FUNDO SINTETICO 0,9L CINZA MEDIO"},{"CODPROD":"1626","DESCRICAO":"FUNDO GALVANIZADO 3,6L BRANCO"},{"CODPROD":"1627","DESCRICAO":"FUNDO GALVANIZADO 0,9L BRANCO"},{"CODPROD":"1637","DESCRICAO":"ESMALTE SINT BRILHANTE 0,9L BRANCO NEVE"},{"CODPROD":"1639","DESCRICAO":"FUNDO SERRALHEIRO 3,6L CINZA"},{"CODPROD":"1641","DESCRICAO":"FUNDO NIVELADOR 3,6L BRANCO"},{"CODPROD":"1642","DESCRICAO":"FUNDO NIVELADOR 0,9L BRANCO"},{"CODPROD":"1643","DESCRICAO":"FUNDO E ACABAMENTO 18L AMARELO OURO"},{"CODPROD":"1644","DESCRICAO":"FUNDO E ACABAMENTO 18L AZUL DEL REY"},{"CODPROD":"1645","DESCRICAO":"FUNDO E ACABAMENTO 18L AZUL FRANCA"},{"CODPROD":"1646","DESCRICAO":"FUNDO E ACABAMENTO 18L BRANCO"},{"CODPROD":"1647","DESCRICAO":"FUNDO E ACABAMENTO 18L CINZA MEDIO"},{"CODPROD":"1649","DESCRICAO":"FUNDO E ACABAMENTO 3,6L AMARELO OURO"},{"CODPROD":"1650","DESCRICAO":"FUNDO E ACABAMENTO 3,6L AZUL DEL REY"},{"CODPROD":"1651","DESCRICAO":"FUNDO E ACABAMENTO 3,6L BRANCO"},{"CODPROD":"1652","DESCRICAO":"FUNDO E ACABAMENTO 3,6L AZUL FRANCA"},{"CODPROD":"1653","DESCRICAO":"FUNDO E ACABAMENTO 3,6L CINZA MEDIO"},{"CODPROD":"1654","DESCRICAO":"FUNDO E ACABAMENTO 3,6L PLATINA"},{"CODPROD":"1655","DESCRICAO":"SELADORA CONCENTRADA P MADEIRA 3,6L"},{"CODPROD":"1656","DESCRICAO":"SELADORA CONCENTRADA P MADEIRA 0,9L"},{"CODPROD":"1658","DESCRICAO":"VERNIZ COPAL KOKAR 3,6L"},{"CODPROD":"1659","DESCRICAO":"VERNIZ COPAL KOKAR 0,9L"},{"CODPROD":"1661","DESCRICAO":"VERNIZ FILTRO SOLAR 0,9L INCOLOR"},{"CODPROD":"1662","DESCRICAO":"VERNIZ FILTRO SOLAR 3,6L INCOLOR"},{"CODPROD":"1664","DESCRICAO":"VERNIZ FILTRO SOLAR 0,9L MOGNO"},{"CODPROD":"1665","DESCRICAO":"VERNIZ FILTRO SOLAR 3,6L MOGNO"},{"CODPROD":"1667","DESCRICAO":"VERNIZ FILTRO SOLAR 0,9L IMBUIA"},{"CODPROD":"1668","DESCRICAO":"VERNIZ FILTRO SOLAR 3,6L IMBUIA"},{"CODPROD":"1671","DESCRICAO":"MASSA PARA MADEIRA 5,5KG "},{"CODPROD":"1672","DESCRICAO":"MASSA PARA MADEIRA 1,3KG"},{"CODPROD":"1690","DESCRICAO":"AGUARRAS KOKAR 0,9L"},{"CODPROD":"1691","DESCRICAO":"THINNER 5500 KOKAR 0,9L"},{"CODPROD":"1694","DESCRICAO":"AGUARRAS KOKAR 5,0L"},{"CODPROD":"1695","DESCRICAO":"THINNER 5500 KOKAR 5,0L"},{"CODPROD":"1722","DESCRICAO":"STANDARD FS ULTRA 18L NEVOA"},{"CODPROD":"1735","DESCRICAO":"THINNER 5500 KOKAR 200L"},{"CODPROD":"1810","DESCRICAO":"BASE NIVELADORA INTERNA KOKAR 15KG"},{"CODPROD":"1829","DESCRICAO":"THINNER 5500 KOKAR 18L"},{"CODPROD":"1838","DESCRICAO":"FUNDO E ACABAMENTO 18L VERDE FOLHA"},{"CODPROD":"1839","DESCRICAO":"FUNDO E ACABAMENTO 3,6L VERDE FOLHA"},{"CODPROD":"1847","DESCRICAO":"TEXTURA RISCADA 20KG BRANCO GELO"},{"CODPROD":"1850","DESCRICAO":"TEXTURA RISCADA 20KG PALHA"},{"CODPROD":"1852","DESCRICAO":"TEXTURA RISCADA 20KG AREIA"},{"CODPROD":"1859","DESCRICAO":"PISO PREMIUM FS 18L CINZA ESCURO"},{"CODPROD":"1860","DESCRICAO":"PISO PREMIUM FS 3,6L CINZA ESCURO"},{"CODPROD":"1891","DESCRICAO":"ESMALTE SINT BRILHANTE 3,6L AMARELO SEGU"},{"CODPROD":"1897","DESCRICAO":"STANDARD FS ULTRA 3,6L CINZA PRATEADO"},{"CODPROD":"1900","DESCRICAO":"FIT ACR FS ECONOMICO 3,6L AREIA"},{"CODPROD":"1929","DESCRICAO":"TEXTURA TRAD 20KG LICOR DE CAFE"},{"CODPROD":"1955","DESCRICAO":"TEXTURA RISC 20KG DOCE DE LEITE"},{"CODPROD":"2039","DESCRICAO":"ESMALTE SINT BRILHANTE 3,6L TERRACOTA"},{"CODPROD":"2049","DESCRICAO":"FUNDO SERRALHEIRO 18L VERMELHO OXIDO"},{"CODPROD":"2062","DESCRICAO":"ESMALTE SINT BRILHANTE 0,9L AMARELO SEGU"},{"CODPROD":"2064","DESCRICAO":"ESMALTE SINT BRILHANTE 3,6L VERMELHO SEG"},{"CODPROD":"2065","DESCRICAO":"ESMALTE SINT BRILHANTE 0,9L VERMELHO SEG"},{"CODPROD":"2112","DESCRICAO":"STANDARD FS 18L BRANCO GELO "},{"CODPROD":"2113","DESCRICAO":"STANDARD FS 3,6L BRANCO GELO "},{"CODPROD":"2114","DESCRICAO":"STANDARD FS 18L CONCRETO "},{"CODPROD":"2115","DESCRICAO":"STANDARD FS 3,6L CONCRETO "},{"CODPROD":"2116","DESCRICAO":"STANDARD FS 18L AREIA "},{"CODPROD":"2117","DESCRICAO":"STANDARD FS 3,6L AREIA"},{"CODPROD":"2119","DESCRICAO":"STANDARD FS 18L BRANCO NEVE"},{"CODPROD":"2120","DESCRICAO":"STANDARD FS 3,6L BRANCO NEVE"},{"CODPROD":"2121","DESCRICAO":"STANDARD FS 18L VERDE LIMAO "},{"CODPROD":"2122","DESCRICAO":"STANDARD FS 3,6L VERDE LIMAO"},{"CODPROD":"2123","DESCRICAO":"STANDARD FS 18L AMARELO CANARIO"},{"CODPROD":"2124","DESCRICAO":"STANDARD FS 3,6L AMARELO CANARIO"},{"CODPROD":"2125","DESCRICAO":"STANDARD FS 18L AMARELO SOL "},{"CODPROD":"2126","DESCRICAO":"STANDARD FS 3,6L AMARELO SOL "},{"CODPROD":"2129","DESCRICAO":"STANDARD FS 18L AZUL OCEANO"},{"CODPROD":"2130","DESCRICAO":"STANDARD FS 3,6L AZUL OCEANO "},{"CODPROD":"2133","DESCRICAO":"STANDARD FS 3,6L CAFE COM LEITE "},{"CODPROD":"2134","DESCRICAO":"STANDARD FS 18L CAFE COM LEITE"},{"CODPROD":"2135","DESCRICAO":"STANDARD FS 3,6L CAMURCA"},{"CODPROD":"2136","DESCRICAO":"STANDARD FS 18L CAMURCA"},{"CODPROD":"2137","DESCRICAO":"STANDARD FS 3,6L CINZA AVELUDADO "},{"CODPROD":"2138","DESCRICAO":"STANDARD FS 18L CINZA AVELUDADO "},{"CODPROD":"2139","DESCRICAO":"STANDARD FS 3,6L ERVA DOCE"},{"CODPROD":"2141","DESCRICAO":"STANDARD FS 3,6L LARANJA"},{"CODPROD":"2142","DESCRICAO":"STANDARD FS 18L LARANJA"},{"CODPROD":"2147","DESCRICAO":"STANDARD FS 18L PALHA "},{"CODPROD":"2148","DESCRICAO":"STANDARD FS 3,6L PALHA "},{"CODPROD":"2149","DESCRICAO":"STANDARD FS 18L PEROLA "},{"CODPROD":"2150","DESCRICAO":"STANDARD FS 3,6L PEROLA "},{"CODPROD":"2157","DESCRICAO":"STANDARD FS 18L VERDE ESPERANCA"},{"CODPROD":"2158","DESCRICAO":"STANDARD FS 3,6L VERDE ESPERANCA"},{"CODPROD":"2159","DESCRICAO":"STANDARD FS 18L VERDE KIWI "},{"CODPROD":"2160","DESCRICAO":"STANDARD FS 3,6L VERDE KIWI "},{"CODPROD":"2166","DESCRICAO":"STANDARD FS 18L AMARELO REAL "},{"CODPROD":"2167","DESCRICAO":"STANDARD FS 3,6L AMARELO REAL "},{"CODPROD":"2168","DESCRICAO":"STANDARD FS 18L LILAS"},{"CODPROD":"2169","DESCRICAO":"STANDARD FS 3,6L LILAS"},{"CODPROD":"2170","DESCRICAO":"STANDARD FS 18L VERDE MUSGO "},{"CODPROD":"2171","DESCRICAO":"STANDARD FS 3,6L VERDE MUSGO"},{"CODPROD":"2174","DESCRICAO":"STANDARD FS 18L CHOCOLATE "},{"CODPROD":"2175","DESCRICAO":"STANDARD FS 3,6L CHOCOLATE"},{"CODPROD":"2192","DESCRICAO":"TEXTURA TRADICIONAL 15KG MRV2013-01"},{"CODPROD":"2193","DESCRICAO":"TEXTURA TRADICIONAL 15KG MRV2013-02"},{"CODPROD":"2204","DESCRICAO":"TEXTURA TRADICIONAL 15KG MRV2013-03"},{"CODPROD":"2205","DESCRICAO":"TEXTURA TRADICIONAL 15KG MRV2013-04"},{"CODPROD":"2206","DESCRICAO":"TEXTURA TRADICIONAL 15KG MRV2013-05"},{"CODPROD":"2207","DESCRICAO":"TEXTURA TRADICIONAL 15KG MRV2013-07"},{"CODPROD":"2208","DESCRICAO":"TEXTURA TRADICIONAL 15KG MRV2013-08"},{"CODPROD":"2209","DESCRICAO":"TEXTURA TRADICIONAL 15KG MRV2013-09"},{"CODPROD":"2210","DESCRICAO":"TEXTURA TRADICIONAL 15KG MRV2013-06"},{"CODPROD":"2211","DESCRICAO":"TEXTURA TRADICIONAL 15KG MRV2013-10"},{"CODPROD":"2212","DESCRICAO":"TEXTURA TRADICIONAL 15KG MRV2013-11"},{"CODPROD":"2242","DESCRICAO":"FUNDO SERRALHEIRO 18L VERDE"},{"CODPROD":"2243","DESCRICAO":"FUNDO SERRALHEIRO 3,6L VERDE"},{"CODPROD":"2244","DESCRICAO":"FUNDO SERRALHEIRO 0,9L VERDE"},{"CODPROD":"2259","DESCRICAO":"GRANULADO LUME 25KG BRANCO GELO"},{"CODPROD":"2260","DESCRICAO":"GRANULADO LUME 25KG BRANCO NEVE"},{"CODPROD":"2261","DESCRICAO":"GRANULADO LUME 25KG ANDIROBA"},{"CODPROD":"2262","DESCRICAO":"GRANULADO LUME 25KG CAMURCA"},{"CODPROD":"2263","DESCRICAO":"GRANULADO LUME 25KG AREIA"},{"CODPROD":"2264","DESCRICAO":"GRANULADO LUME 25KG BARBANTE"},{"CODPROD":"2265","DESCRICAO":"GRANULADO MINERAIS 25KG CRISTAL "},{"CODPROD":"2266","DESCRICAO":"GRANULADO MINERAIS 25KG ESMERALDA"},{"CODPROD":"2267","DESCRICAO":"GRANULADO MINERAIS 25KG HEMATITA"},{"CODPROD":"2268","DESCRICAO":"GRANULADO MINERAIS 25KG PRATA"},{"CODPROD":"2269","DESCRICAO":"GRANULADO MINERAIS 25KG RUBI"},{"CODPROD":"2270","DESCRICAO":"GRANULADO MINERAIS 25KG TOPAZIO"},{"CODPROD":"2277","DESCRICAO":"GRANULADO LUME 25KG ACAI"},{"CODPROD":"2278","DESCRICAO":"GRANULADO LUME 25KG AZUL ARARA"},{"CODPROD":"2279","DESCRICAO":"GRANULADO LUME 25KG PRETO ONIX"},{"CODPROD":"2280","DESCRICAO":"GRANULADO LUME 25KG ROXO PAVAO"},{"CODPROD":"2281","DESCRICAO":"GRANULADO LUME 25KG VERDE MUSGO"},{"CODPROD":"2282","DESCRICAO":"GRANULADO LUME 25KG VERMELHO PAIXAO"},{"CODPROD":"2302","DESCRICAO":"REV MARMORE 3,9KG BRANCO NEVE"},{"CODPROD":"2303","DESCRICAO":"REV MARMORE 4,8KG CAPIM DOURADO"},{"CODPROD":"2304","DESCRICAO":"REV MARMORE 4,8KG AZUL ARARA"},{"CODPROD":"2305","DESCRICAO":"REV MARMORE 4,8KG VERMELHO PAIXAO"},{"CODPROD":"2306","DESCRICAO":"REV MARMORE 4,8KG VERDE IMPERIAL"},{"CODPROD":"2307","DESCRICAO":"REV MARMORE 4,8KG CINZA MEDIEVAL"},{"CODPROD":"2308","DESCRICAO":"REV CIMENTO QUEIMADO 1,2KG AZUL SERENO"},{"CODPROD":"2309","DESCRICAO":"REV CIMENTO QUEIMADO 4,8KG CONCRETO"},{"CODPROD":"2310","DESCRICAO":"REV CIMENTO QUEIMADO 4,8KG MARSALLA"},{"CODPROD":"2311","DESCRICAO":"REV CIMENTO QUEIMADO 4,8KG VERDE SALVIA"},{"CODPROD":"2312","DESCRICAO":"REV CIMENTO QUEIMADO 4,8KG CINZA AVELUD"},{"CODPROD":"2321","DESCRICAO":"FUNDO SERRALHEIRO 3,6L PRETO"},{"CODPROD":"2322","DESCRICAO":"FUNDO SERRALHEIRO 0,9L PRETO"},{"CODPROD":"2326","DESCRICAO":"ESMALTE SINT BRILHANTE 18L BRANCO NEVE"},{"CODPROD":"2328","DESCRICAO":"REV CIMENTO QUEIMADO 4,8KG AZUL SERENO"},{"CODPROD":"2330","DESCRICAO":"GRANULADO LUME 25KG CARCARA"},{"CODPROD":"2334","DESCRICAO":"TEXTURA RISCADA 15KG MRV2013-11"},{"CODPROD":"2344","DESCRICAO":"TEXTURA RISCADA 15KG MRV2013-08"},{"CODPROD":"2398","DESCRICAO":"GRANULADO LUME 25KG CHOCOLATE"},{"CODPROD":"2399","DESCRICAO":"GRANULADO LUME 25KG CINZA PRATEADO"},{"CODPROD":"2400","DESCRICAO":"GRANULADO LUME 25KG CINZA TAUPE"},{"CODPROD":"2401","DESCRICAO":"GRANULADO LUME 25KG JADE"},{"CODPROD":"2402","DESCRICAO":"GRANULADO LUME 25KG LUA CHEIA"},{"CODPROD":"2403","DESCRICAO":"GRANULADO LUME 25KG MARSALLA"},{"CODPROD":"2404","DESCRICAO":"GRANULADO LUME 25KG MENTA"},{"CODPROD":"2405","DESCRICAO":"GRANULADO LUME 25KG NEVOA"},{"CODPROD":"2406","DESCRICAO":"GRANULADO LUME 25KG TITANIO"},{"CODPROD":"2409","DESCRICAO":"MICRO RISCADO SUBLIME 25KG BARBANTE"},{"CODPROD":"2410","DESCRICAO":"MICRO RISCADO SUBLIME 25KG BANCO GELO"},{"CODPROD":"2411","DESCRICAO":"MICRO RISCADO SUBLIME 25KG BANCO NEVE"},{"CODPROD":"2417","DESCRICAO":"MICRO RISCADO SUBLIME 25KG JADE"},{"CODPROD":"2421","DESCRICAO":"MICRO RISCADO SUBLIME 25KG NEVOA"},{"CODPROD":"2439","DESCRICAO":"REV MARMORE 4,8KG CHOCOLATE"},{"CODPROD":"2440","DESCRICAO":"REV MARMORE 4,8KG PRETO"},{"CODPROD":"2441","DESCRICAO":"REV CIMENTO QUEIMADO 4,8KG CERRADO"},{"CODPROD":"2445","DESCRICAO":"PRIMMER ACABAMENTO CINZA ALEUTA 200L"},{"CODPROD":"2455","DESCRICAO":"REV MARMORE 1,2KG AZUL ARARA"},{"CODPROD":"2456","DESCRICAO":"REV MARMORE 1,2KG VERMELHO PAIXAO"},{"CODPROD":"2457","DESCRICAO":"REV MARMORE 1,2KG VERDE IMPERIAL"},{"CODPROD":"2458","DESCRICAO":"REV MARMORE 1,2KG PRETO"},{"CODPROD":"2459","DESCRICAO":"REV MARMORE 1,2KG CHOCOLATE"},{"CODPROD":"2460","DESCRICAO":"REV MARMORE 1,2KG CINZA MEDIEVAL"},{"CODPROD":"2461","DESCRICAO":"REV MARMORE 1,2KG CAPIM DOURADO"},{"CODPROD":"2462","DESCRICAO":"REV MARMORE 0,975KG BRANCO NEVE"},{"CODPROD":"2464","DESCRICAO":"REV CIMENTO QUEIMADO 1,2KG CINZA AVELUD"},{"CODPROD":"2465","DESCRICAO":"REV CIMENTO QUEIMADO 1,2KG CERRADO"},{"CODPROD":"2466","DESCRICAO":"REV CIMENTO QUEIMADO 1,2KG CONCRETO"},{"CODPROD":"2467","DESCRICAO":"REV CIMENTO QUEIMADO 1,2KG MARSALLA"},{"CODPROD":"2468","DESCRICAO":"REV CIMENTO QUEIMADO 1,2KG VERDE SALVIA"},{"CODPROD":"2471","DESCRICAO":"CERA PASTA SUBLIME INCOLOR 0,200 G"},{"CODPROD":"2477","DESCRICAO":"AGUARRAS KOKAR 200L"},{"CODPROD":"2486","DESCRICAO":"STANDARD FS 3,6L TERRACOTA "},{"CODPROD":"2487","DESCRICAO":"STANDARD FS 18L TERRACOTA "},{"CODPROD":"2503","DESCRICAO":"TEXTURA TRADICIONAL 15KG CONCRETO L15\/19"},{"CODPROD":"2512","DESCRICAO":"ESMALTE SINT BRILHANTE ALUMINIO 198L"},{"CODPROD":"2527","DESCRICAO":"TEXTURA RISCADA 15KG MRV2013-01"},{"CODPROD":"2529","DESCRICAO":"TEXTURA RISCADA 15KG MRV2013-02"},{"CODPROD":"2532","DESCRICAO":"FIT SELADOR ACRILICO KOKAR 16L LONDRES"},{"CODPROD":"2545","DESCRICAO":"TEXTURA TRADICIONAL 25KG AREIA"},{"CODPROD":"2547","DESCRICAO":"TEXTURA TRADICIONAL 25KG CAMURCA"},{"CODPROD":"2548","DESCRICAO":"TEXTURA TRADICIONAL 25KG CHOCOLATE"},{"CODPROD":"2552","DESCRICAO":"PREMIUM FOSCO 3,6L LARANJA"},{"CODPROD":"2554","DESCRICAO":"FUNDO GALVANIZADO 0,9L CINZA MEDIO"},{"CODPROD":"2555","DESCRICAO":"FUNDO GALVANIZADO 3,6L CINZA MEDIO"},{"CODPROD":"2562","DESCRICAO":"FUNDO E ACABAMENTO 18L PRETO"},{"CODPROD":"2563","DESCRICAO":"FUNDO E ACABAMENTO 3,6L PRETO"},{"CODPROD":"2567","DESCRICAO":"TEXTURA TRADICIONAL 25KG VIENA L10\/1"},{"CODPROD":"2572","DESCRICAO":"STANDARD FS 3,6L BEGE FAVORITO"},{"CODPROD":"2573","DESCRICAO":"STANDARD FS 3,6L GRISALHOS L28\/19"},{"CODPROD":"2575","DESCRICAO":"STANDARD FS 18L BEGE FAVORITO"},{"CODPROD":"2576","DESCRICAO":"STANDARD FS 18L GRISALHO L28\/19"},{"CODPROD":"2584","DESCRICAO":"STANDARD FS 18L CAPUCCINO"},{"CODPROD":"2608","DESCRICAO":"TEXTURA TRADICIONAL 25KG GRISALHO"},{"CODPROD":"2610","DESCRICAO":"STANDARD FS 18L AZUL PROFUNDO"},{"CODPROD":"2616","DESCRICAO":"ESMALTE SINT BRILHANTE 18L CINZA MEDIO"},{"CODPROD":"2627","DESCRICAO":"FUNDO E ACABAMENTO 18L AZUL ROYAL"},{"CODPROD":"2664","DESCRICAO":"TEXTURA RISCADA 25KG CAMURCA"},{"CODPROD":"2669","DESCRICAO":"FUNDO E ACABAMENTO 18L TERRACOTA"},{"CODPROD":"2697","DESCRICAO":"FIT ACR FS ECONOMICO 3,6L ARAPONGA"},{"CODPROD":"2698","DESCRICAO":"FIT ACR FS ECONOMICO 3,6L AMAZONITA"},{"CODPROD":"2699","DESCRICAO":"FIT ACR FS ECONOMICO 3,6L LILAS"},{"CODPROD":"2700","DESCRICAO":"FIT ACR FS ECONOMICO 3,6L SANHACU"},{"CODPROD":"2702","DESCRICAO":"FIT ACR FS ECONOMICO 16L ARAPONGA"},{"CODPROD":"2703","DESCRICAO":"FIT ACR FS ECONOMICO 16L AMAZONITA"},{"CODPROD":"2704","DESCRICAO":"FIT ACR FS ECONOMICO 16L LILAS"},{"CODPROD":"2705","DESCRICAO":"FIT ACR FS ECONOMICO 16L SANHACU"},{"CODPROD":"2735","DESCRICAO":"ECONOMICO FOSCO 18L CINZA PRATEADO"},{"CODPROD":"2737","DESCRICAO":"ECONOMICO FOSCO 18L ARAPONGA"},{"CODPROD":"2738","DESCRICAO":"ECONOMICO FOSCO 18L NEVOA"},{"CODPROD":"2739","DESCRICAO":"ECONOMICO FOSCO 18L CINZA AVELUDADO"},{"CODPROD":"2740","DESCRICAO":"ECONOMICO FOSCO 18L MARSALLA"},{"CODPROD":"2744","DESCRICAO":"ECONOMICO FOSCO 18L BARBANTE"},{"CODPROD":"2745","DESCRICAO":"ECONOMICO FOSCO 18L LUA CHEIA"},{"CODPROD":"2746","DESCRICAO":"ECONOMICO FOSCO 18L BEGE FAVORITO"},{"CODPROD":"2747","DESCRICAO":"ECONOMICO FOSCO 18L ANDIROBA"},{"CODPROD":"2748","DESCRICAO":"ECONOMICO FOSCO 18L CASTANHEIRA"},{"CODPROD":"2751","DESCRICAO":"ECONOMICO FOSCO 18L VERDE MENTA"},{"CODPROD":"2752","DESCRICAO":"ECONOMICO FOSCO 18L AMAZONITA"},{"CODPROD":"2755","DESCRICAO":"ECONOMICO FOSCO 18L ANOITECER"},{"CODPROD":"2757","DESCRICAO":"ECONOMICO FOSCO 18L FERVEDOURO"},{"CODPROD":"2759","DESCRICAO":"ECONOMICO FOSCO 18L BOTO ROSA"},{"CODPROD":"2761","DESCRICAO":"ECONOMICO FOSCO 18L SANHACU"},{"CODPROD":"2763","DESCRICAO":"ECONOMICO FOSCO 3,6L CINZA PRATEADO"},{"CODPROD":"2765","DESCRICAO":"ECONOMICO FOSCO 3,6L ARAPONGA"},{"CODPROD":"2766","DESCRICAO":"ECONOMICO FOSCO 3,6L NEVOA"},{"CODPROD":"2767","DESCRICAO":"ECONOMICO FOSCO 3,6L CINZA AVELUDADO"},{"CODPROD":"2768","DESCRICAO":"ECONOMICO FOSCO 3,6L MARSALLA"},{"CODPROD":"2772","DESCRICAO":"ECONOMICO FOSCO 3,6L BARBANTE"},{"CODPROD":"2773","DESCRICAO":"ECONOMICO FOSCO 3,6L LUA CHEIA"},{"CODPROD":"2774","DESCRICAO":"ECONOMICO FOSCO 3,6L BEGE FAVORITO"},{"CODPROD":"2775","DESCRICAO":"ECONOMICO FOSCO 3,6L ANDIROBA"},{"CODPROD":"2776","DESCRICAO":"ECONOMICO FOSCO 3,6L CASTANHEIRA"},{"CODPROD":"2779","DESCRICAO":"ECONOMICO FOSCO 3,6L VERDE MENTA"},{"CODPROD":"2780","DESCRICAO":"ECONOMICO FOSCO 3,6L AMAZONITA"},{"CODPROD":"2784","DESCRICAO":"ECONOMICO FOSCO 3,6L FERVEDOURO"},{"CODPROD":"2787","DESCRICAO":"ECONOMICO FOSCO 3,6L BOTO ROSA"},{"CODPROD":"2789","DESCRICAO":"ECONOMICO FOSCO 3,6L SANHACU"},{"CODPROD":"2790","DESCRICAO":"TEXTURA TRADICIONAL 15KG CAMURCA"},{"CODPROD":"2819","DESCRICAO":"STANDARD FS 18L SEIXO BRANCO"},{"CODPROD":"2820","DESCRICAO":"STANDARD FS 18L CINZA PRATEADO"},{"CODPROD":"2822","DESCRICAO":"STANDARD FS 18L AZUL SERENO"},{"CODPROD":"2823","DESCRICAO":"STANDARD FS 18L ARAPONGA"},{"CODPROD":"2824","DESCRICAO":"STANDARD FS 18L NEVOA"},{"CODPROD":"2825","DESCRICAO":"STANDARD FS 18L MARSALLA"},{"CODPROD":"2826","DESCRICAO":"STANDARD FS 18L CINZA TAUPE"},{"CODPROD":"2827","DESCRICAO":"STANDARD FS 18L TITANIO"},{"CODPROD":"2829","DESCRICAO":"STANDARD FS 18L BARBANTE"},{"CODPROD":"2830","DESCRICAO":"STANDARD FS 18L LUA CHEIA"},{"CODPROD":"2831","DESCRICAO":"STANDARD FS 18L ANDIROBA"},{"CODPROD":"2832","DESCRICAO":"STANDARD FS 18L CASTANHEIRA"},{"CODPROD":"2833","DESCRICAO":"STANDARD FS 18L CASCALHO DE RIO"},{"CODPROD":"2834","DESCRICAO":"STANDARD FS 18L CARCARA"},{"CODPROD":"2835","DESCRICAO":"STANDARD FS 18L JENIPAPO"},{"CODPROD":"2836","DESCRICAO":"STANDARD FS 18L CERAMICA"},{"CODPROD":"2838","DESCRICAO":"STANDARD FS 18L VERDE MENTA"},{"CODPROD":"2839","DESCRICAO":"STANDARD FS 18L AMAZONITA"},{"CODPROD":"2841","DESCRICAO":"STANDARD FS 18L SANHACU"},{"CODPROD":"2842","DESCRICAO":"STANDARD FS 18L ANOITECER"},{"CODPROD":"2843","DESCRICAO":"STANDARD FS 18L FERVEDOURO "},{"CODPROD":"2844","DESCRICAO":"STANDARD FS 18L TURMALINA AZUL"},{"CODPROD":"2845","DESCRICAO":"STANDARD FS 18L VITORIA REGIA"},{"CODPROD":"2847","DESCRICAO":"STANDARD FS 18L COPAIBA"},{"CODPROD":"2848","DESCRICAO":"STANDARD FS 18L IPE ROSA"},{"CODPROD":"2849","DESCRICAO":"STANDARD FS 3,6L SEIXO BRANCO"},{"CODPROD":"2850","DESCRICAO":"STANDARD FS 3,6L CINZA PRATEADO"},{"CODPROD":"2851","DESCRICAO":"STANDARD FS 3,6L ARAPONGA"},{"CODPROD":"2852","DESCRICAO":"STANDARD FS 3,6L NEVOA"},{"CODPROD":"2853","DESCRICAO":"STANDARD FS 3,6L AZUL SERENO"},{"CODPROD":"2854","DESCRICAO":"STANDARD FS 3,6L MARSALLA"},{"CODPROD":"2855","DESCRICAO":"STANDARD FS 3,6L CINZA TAUPE"},{"CODPROD":"2856","DESCRICAO":"STANDARD FS 3,6L TITANIO"},{"CODPROD":"2858","DESCRICAO":"STANDARD FS 3,6L BARBANTE"},{"CODPROD":"2859","DESCRICAO":"STANDARD FS 3,6L LUA CHEIA"},{"CODPROD":"2860","DESCRICAO":"STANDARD FS 3,6L ANDIROBA"},{"CODPROD":"2861","DESCRICAO":"STANDARD FS 3,6L CASTANHEIRA"},{"CODPROD":"2862","DESCRICAO":"STANDARD FS 3,6L CASCALHO DE RIO"},{"CODPROD":"2863","DESCRICAO":"STANDARD FS 3,6L CARCARA"},{"CODPROD":"2864","DESCRICAO":"STANDARD FS 3,6L JENIPAPO"},{"CODPROD":"2865","DESCRICAO":"STANDARD FS 3,6L CERAMICA"},{"CODPROD":"2867","DESCRICAO":"STANDARD FS 3,6L VERDE MENTA"},{"CODPROD":"2868","DESCRICAO":"STANDARD FS 3,6L AMAZONITA"},{"CODPROD":"2869","DESCRICAO":"STANDARD FS 3,6L BRANCO SIRIEMA"},{"CODPROD":"2870","DESCRICAO":"STANDARD FS 3,6L SANHACU"},{"CODPROD":"2871","DESCRICAO":"STANDARD FS 3,6L ANOITECER"},{"CODPROD":"2872","DESCRICAO":"STANDARD FS 3,6L FERVEDOURO "},{"CODPROD":"2873","DESCRICAO":"STANDARD FS 3,6L TURMALINA AZUL"},{"CODPROD":"2874","DESCRICAO":"STANDARD FS 3,6L VITORIA REGIA"},{"CODPROD":"2876","DESCRICAO":"STANDARD FS 3,6L COPAIBA"},{"CODPROD":"2877","DESCRICAO":"STANDARD FS 3,6L IPE ROSA"},{"CODPROD":"2907","DESCRICAO":"FIT ACR FS ECONOMICO 16L MARFIM"},{"CODPROD":"2908","DESCRICAO":"FIT ACR FS ECONOMICO 3,6L MARFIM"},{"CODPROD":"2910","DESCRICAO":"ECONOMICO FOSCO 3,6L MARFIM"},{"CODPROD":"2911","DESCRICAO":"ECONOMICO FOSCO 18L MARFIM"},{"CODPROD":"2914","DESCRICAO":"STANDARD FS 3,6L MARFIM"},{"CODPROD":"2915","DESCRICAO":"STANDARD SB 3,6L MARFIM"},{"CODPROD":"2916","DESCRICAO":"STANDARD FS 18L MARFIM"},{"CODPROD":"2917","DESCRICAO":"STANDARD SB 18L MARFIM"},{"CODPROD":"2919","DESCRICAO":"PREMIUM FOSCO 3,6L MARFIM"},{"CODPROD":"2921","DESCRICAO":"PREMIUM SEMIBRILHO 3,6L MARFIM"},{"CODPROD":"2922","DESCRICAO":"PREMIUM FOSCO 18L MARFIM"},{"CODPROD":"2923","DESCRICAO":"PREMIUM SEMIBRILHO 18L MARFIM"},{"CODPROD":"2925","DESCRICAO":"PREMIUM FOSCO 3,6L VERMELHO AMOR"},{"CODPROD":"2926","DESCRICAO":"PREMIUM FOSCO 18L VERMELHO AMOR"},{"CODPROD":"2928","DESCRICAO":"PREMIUM SEMIBRILHO 3,6L VERMELHO AMOR"},{"CODPROD":"2929","DESCRICAO":"PREMIUM SEMIBRILHO 18L VERMELHO AMOR"},{"CODPROD":"2938","DESCRICAO":"STANDARD SB 18L SEIXO BRANCO"},{"CODPROD":"2939","DESCRICAO":"STANDARD SB 18L CINZA PRATEADO"},{"CODPROD":"2940","DESCRICAO":"STANDARD SB 18L AZUL SERENO"},{"CODPROD":"2941","DESCRICAO":"STANDARD SB 18L ARAPONGA"},{"CODPROD":"2942","DESCRICAO":"STANDARD SB 18L NEVOA"},{"CODPROD":"2943","DESCRICAO":"STANDARD SB 18L CINZA TAUPE"},{"CODPROD":"2944","DESCRICAO":"STANDARD SB 18L TITANIO"},{"CODPROD":"2946","DESCRICAO":"STANDARD SB 18L BARBANTE"},{"CODPROD":"2947","DESCRICAO":"STANDARD SB 18L LUA CHEIA"},{"CODPROD":"2948","DESCRICAO":"STANDARD SB 18L ANDIROBA"},{"CODPROD":"2949","DESCRICAO":"STANDARD SB 18L CASTANHEIRA"},{"CODPROD":"2950","DESCRICAO":"STANDARD SB 18L MARSALLA"},{"CODPROD":"2952","DESCRICAO":"STANDARD SB 18L CARCARA"},{"CODPROD":"2953","DESCRICAO":"STANDARD SB 18L JENIPAPO"},{"CODPROD":"2956","DESCRICAO":"STANDARD SB 18L VERDE MENTA"},{"CODPROD":"2957","DESCRICAO":"STANDARD SB 18L AMAZONITA"},{"CODPROD":"2959","DESCRICAO":"STANDARD SB 18L SANHACU"},{"CODPROD":"2960","DESCRICAO":"STANDARD SB 18L ANOITECER"},{"CODPROD":"2961","DESCRICAO":"STANDARD SB 18L FERVEDOURO "},{"CODPROD":"2962","DESCRICAO":"STANDARD SB 18L TURMALINA AZUL"},{"CODPROD":"2963","DESCRICAO":"STANDARD SB 18L VITORIA REGIA"},{"CODPROD":"2965","DESCRICAO":"STANDARD SB 18L COPAIBA"},{"CODPROD":"2966","DESCRICAO":"STANDARD SB 18L IPE ROSA"},{"CODPROD":"2967","DESCRICAO":"STANDARD SB 3,6L SEIXO BRANCO"},{"CODPROD":"2968","DESCRICAO":"STANDARD SB 3,6L CINZA PRATEADO"},{"CODPROD":"2969","DESCRICAO":"STANDARD SB 3,6L AZUL SERENO"},{"CODPROD":"2970","DESCRICAO":"STANDARD SB 3,6L ARAPONGA"},{"CODPROD":"2971","DESCRICAO":"STANDARD SB 3,6L NEVOA"},{"CODPROD":"2972","DESCRICAO":"STANDARD SB 3,6L MARSALLA"},{"CODPROD":"2973","DESCRICAO":"STANDARD SB 3,6L CINZA TAUPE"},{"CODPROD":"2974","DESCRICAO":"STANDARD SB 3,6L TITANIO"},{"CODPROD":"2976","DESCRICAO":"STANDARD SB 3,6L BARBANTE"},{"CODPROD":"2977","DESCRICAO":"STANDARD SB 3,6L LUA CHEIA"},{"CODPROD":"2978","DESCRICAO":"STANDARD SB 3,6L ANDIROBA"},{"CODPROD":"2979","DESCRICAO":"STANDARD SB 3,6L CASTANHEIRA"},{"CODPROD":"2981","DESCRICAO":"STANDARD SB 3,6L CARCARA"},{"CODPROD":"2982","DESCRICAO":"STANDARD SB 3,6L JENIPAPO"},{"CODPROD":"2985","DESCRICAO":"STANDARD SB 3,6L VERDE MENTA"},{"CODPROD":"2986","DESCRICAO":"STANDARD SB 3,6L AMAZONITA"},{"CODPROD":"2988","DESCRICAO":"STANDARD SB 3,6L SANHACU"},{"CODPROD":"2989","DESCRICAO":"STANDARD SB 3,6L ANOITECER"},{"CODPROD":"2990","DESCRICAO":"STANDARD SB 3,6L FERVEDOURO "},{"CODPROD":"2991","DESCRICAO":"STANDARD SB 3,6L TURMALINA AZUL"},{"CODPROD":"2992","DESCRICAO":"STANDARD SB 3,6L VITORIA REGIA"},{"CODPROD":"2993","DESCRICAO":"STANDARD SB 3,6L BOTO ROSA"},{"CODPROD":"2994","DESCRICAO":"STANDARD SB 3,6L COPAIBA"},{"CODPROD":"2995","DESCRICAO":"STANDARD SB 3,6L IPE ROSA"},{"CODPROD":"2996","DESCRICAO":"STANDARD SB 3,6L BEGE FAVORITO"},{"CODPROD":"3070","DESCRICAO":"PREMIUM ACET SEDA 3,6L ARAPONGA"},{"CODPROD":"3073","DESCRICAO":"PREMIUM ACET SEDA 3,6L BEGE FAVORITO"},{"CODPROD":"3077","DESCRICAO":"PREMIUM ACET SEDA 3,6L ROSA CHA"},{"CODPROD":"3079","DESCRICAO":"PREMIUM ACET SEDA 3,6L BRANCO SIRIEMA"},{"CODPROD":"3083","DESCRICAO":"PREMIUM FOSCO 18L SEIXO BRANCO"},{"CODPROD":"3084","DESCRICAO":"PREMIUM FOSCO 18L CINZA PRATEADO"},{"CODPROD":"3085","DESCRICAO":"PREMIUM FOSCO 18L AZUL SERENO"},{"CODPROD":"3086","DESCRICAO":"PREMIUM FOSCO 18L ARAPONGA"},{"CODPROD":"3087","DESCRICAO":"PREMIUM FOSCO 18L NEVOA"},{"CODPROD":"3088","DESCRICAO":"PREMIUM FOSCO 18L CINZA AVELUDADO"},{"CODPROD":"3089","DESCRICAO":"PREMIUM FOSCO 18L MARSALLA"},{"CODPROD":"3091","DESCRICAO":"PREMIUM FOSCO 18L CINZA TAUPE"},{"CODPROD":"3092","DESCRICAO":"PREMIUM FOSCO 18L TITANIO"},{"CODPROD":"3093","DESCRICAO":"PREMIUM FOSCO 18L PRETO"},{"CODPROD":"3094","DESCRICAO":"PREMIUM FOSCO 18L ROSA CHA"},{"CODPROD":"3095","DESCRICAO":"PREMIUM FOSCO 18L BARBANTE"},{"CODPROD":"3096","DESCRICAO":"PREMIUM FOSCO 18L LUA CHEIA"},{"CODPROD":"3097","DESCRICAO":"PREMIUM FOSCO 18L BEGE FAVORITO"},{"CODPROD":"3098","DESCRICAO":"PREMIUM FOSCO 18L ANDIROBA"},{"CODPROD":"3099","DESCRICAO":"PREMIUM FOSCO 18L CASTANHEIRA"},{"CODPROD":"3100","DESCRICAO":"PREMIUM FOSCO 18L CASCALHO DE RIO"},{"CODPROD":"3101","DESCRICAO":"PREMIUM FOSCO 18L CARCARA "},{"CODPROD":"3102","DESCRICAO":"PREMIUM FOSCO 18L JENIPAPO"},{"CODPROD":"3103","DESCRICAO":"PREMIUM FOSCO 18L AMARELO SOL"},{"CODPROD":"3104","DESCRICAO":"PREMIUM FOSCO 18L CERAMICA"},{"CODPROD":"3105","DESCRICAO":"PREMIUM FOSCO 18L CARDEAL"},{"CODPROD":"3106","DESCRICAO":"PREMIUM FOSCO 18L VERDE MENTA"},{"CODPROD":"3111","DESCRICAO":"PREMIUM FOSCO 18L AMAZONITA"},{"CODPROD":"3113","DESCRICAO":"PREMIUM FOSCO 18L JADE"},{"CODPROD":"3115","DESCRICAO":"PREMIUM FOSCO 18L BRANCO SIRIEMA"},{"CODPROD":"3118","DESCRICAO":"PREMIUM FOSCO 18L SANHACU"},{"CODPROD":"3119","DESCRICAO":"PREMIUM FOSCO 18L ANOITECER"},{"CODPROD":"3121","DESCRICAO":"PREMIUM FOSCO 18L AZUL PROFUNDO"},{"CODPROD":"3122","DESCRICAO":"PREMIUM FOSCO 18L FERVEDOURO"},{"CODPROD":"3124","DESCRICAO":"PREMIUM FOSCO 18L TURMALINA AZUL"},{"CODPROD":"3127","DESCRICAO":"PREMIUM FOSCO 18L AZUL BEIJA FLOR"},{"CODPROD":"3128","DESCRICAO":"PREMIUM FOSCO 18L VITORIA REGIA"},{"CODPROD":"3129","DESCRICAO":"PREMIUM FOSCO 18L BOTO ROSA"},{"CODPROD":"3130","DESCRICAO":"PREMIUM FOSCO 18L COPAIBA"},{"CODPROD":"3131","DESCRICAO":"PREMIUM FOSCO 18L IPE ROSA"},{"CODPROD":"3132","DESCRICAO":"PREMIUM FOSCO 18L BROMELIA"},{"CODPROD":"3142","DESCRICAO":"PREMIUM FOSCO 3,6L SEIXO BRANCO"},{"CODPROD":"3144","DESCRICAO":"PREMIUM FOSCO 3,6L CINZA PRATEADO"},{"CODPROD":"3146","DESCRICAO":"PREMIUM FOSCO 3,6L AZUL SERENO"},{"CODPROD":"3147","DESCRICAO":"PREMIUM FOSCO 3,6L ARAPONGA"},{"CODPROD":"3149","DESCRICAO":"PREMIUM FOSCO 3,6L NEVOA"},{"CODPROD":"3151","DESCRICAO":"PREMIUM FOSCO 3,6L CINZA AVELUDADO"},{"CODPROD":"3153","DESCRICAO":"PREMIUM FOSCO 3,6L MARSALLA"},{"CODPROD":"3155","DESCRICAO":"PREMIUM FOSCO 3,6L CINZA TAUPE"},{"CODPROD":"3157","DESCRICAO":"PREMIUM FOSCO 3,6L TITANIO"},{"CODPROD":"3159","DESCRICAO":"PREMIUM FOSCO 3,6L PRETO"},{"CODPROD":"3161","DESCRICAO":"PREMIUM FOSCO 3,6L ROSA CHA"},{"CODPROD":"3162","DESCRICAO":"PREMIUM FOSCO 3,6L BARBANTE"},{"CODPROD":"3163","DESCRICAO":"PREMIUM FOSCO 3,6L LUA CHEIA"},{"CODPROD":"3164","DESCRICAO":"PREMIUM FOSCO 3,6L BEGE FAVORITO"},{"CODPROD":"3166","DESCRICAO":"PREMIUM FOSCO 3,6L ANDIROBA"},{"CODPROD":"3168","DESCRICAO":"PREMIUM FOSCO 3,6L CASTANHEIRA"},{"CODPROD":"3170","DESCRICAO":"PREMIUM FOSCO 3,6L CASCALHO DE RIO"},{"CODPROD":"3171","DESCRICAO":"PREMIUM FOSCO 3,6L CARCARA"},{"CODPROD":"3173","DESCRICAO":"PREMIUM FOSCO 3,6L JENIPAPO"},{"CODPROD":"3175","DESCRICAO":"PREMIUM FOSCO 3,6L AMARELO SOL"},{"CODPROD":"3177","DESCRICAO":"PREMIUM FOSCO 3,6L CERAMICA"},{"CODPROD":"3178","DESCRICAO":"PREMIUM FOSCO 3,6L CARDEAL"},{"CODPROD":"3179","DESCRICAO":"PREMIUM FOSCO 3,6L VERDE MENTA"},{"CODPROD":"3180","DESCRICAO":"PREMIUM FOSCO 3,6L AMAZONITA"},{"CODPROD":"3181","DESCRICAO":"PREMIUM FOSCO 3,6L JADE"},{"CODPROD":"3182","DESCRICAO":"PREMIUM FOSCO 3,6L BRANCO SIRIEMA"},{"CODPROD":"3183","DESCRICAO":"PREMIUM FOSCO 3,6L SANHACU"},{"CODPROD":"3184","DESCRICAO":"PREMIUM FOSCO 3,6L ANOITECER"},{"CODPROD":"3185","DESCRICAO":"PREMIUM FOSCO 3,6L AZUL PROFUNDO"},{"CODPROD":"3186","DESCRICAO":"PREMIUM FOSCO 3,6L FERVEDOURO"},{"CODPROD":"3187","DESCRICAO":"PREMIUM FOSCO 3,6L TURMALINA AZUL"},{"CODPROD":"3188","DESCRICAO":"PREMIUM FOSCO 3,6L AZUL BEIJA FLOR"},{"CODPROD":"3189","DESCRICAO":"PREMIUM FOSCO 3,6L VITORIA REGIA"},{"CODPROD":"3190","DESCRICAO":"PREMIUM FOSCO 3,6L BOTO ROSA"},{"CODPROD":"3191","DESCRICAO":"PREMIUM FOSCO 3,6L COPAIBA"},{"CODPROD":"3192","DESCRICAO":"PREMIUM FOSCO 3,6L IPE ROSA"},{"CODPROD":"3193","DESCRICAO":"PREMIUM FOSCO 3,6L BROMELIA"},{"CODPROD":"3197","DESCRICAO":"PREMIUM SEMIBRILHO 18L SEIXO BRANCO"},{"CODPROD":"3199","DESCRICAO":"PREMIUM SEMIBRILHO 18L CINZA PRATEADO"},{"CODPROD":"3200","DESCRICAO":"PREMIUM SEMIBRILHO 18L AZUL SERENO"},{"CODPROD":"3201","DESCRICAO":"PREMIUM SEMIBRILHO 18L ARAPONGA"},{"CODPROD":"3203","DESCRICAO":"PREMIUM SEMIBRILHO 18L NEVOA"},{"CODPROD":"3205","DESCRICAO":"PREMIUM SEMIBRILHO 18L CINZA AVELUDADO"},{"CODPROD":"3206","DESCRICAO":"PREMIUM SEMIBRILHO 18L MARSALLA"},{"CODPROD":"3207","DESCRICAO":"PREMIUM SEMIBRILHO 18L CINZA TAUPE"},{"CODPROD":"3208","DESCRICAO":"PREMIUM SEMIBRILHO 18L TITANIO"},{"CODPROD":"3210","DESCRICAO":"PREMIUM SEMIBRILHO 18L PRETO"},{"CODPROD":"3211","DESCRICAO":"PREMIUM SEMIBRILHO 18L ROSA CHA"},{"CODPROD":"3213","DESCRICAO":"PREMIUM SEMIBRILHO 18L BARBANTE"},{"CODPROD":"3214","DESCRICAO":"PREMIUM SEMIBRILHO 18L LUA CHEIA"},{"CODPROD":"3215","DESCRICAO":"PREMIUM SEMIBRILHO 18L BEGE FAVORITO"},{"CODPROD":"3217","DESCRICAO":"PREMIUM SEMIBRILHO 18L ANDIROBA"},{"CODPROD":"3218","DESCRICAO":"PREMIUM SEMIBRILHO 18L CASTANHEIRA"},{"CODPROD":"3219","DESCRICAO":"PREMIUM SEMIBRILHO 18L CASCALHO DE RIO"},{"CODPROD":"3221","DESCRICAO":"PREMIUM SEMIBRILHO 18L CARCARA"},{"CODPROD":"3227","DESCRICAO":"PREMIUM SEMIBRILHO 18L JENIPAPO"},{"CODPROD":"3228","DESCRICAO":"PREMIUM SEMIBRILHO 18L AMARELO SOL"},{"CODPROD":"3229","DESCRICAO":"PREMIUM SEMIBRILHO 18L CERAMICA"},{"CODPROD":"3230","DESCRICAO":"PREMIUM SEMIBRILHO 18L CARDEAL"},{"CODPROD":"3231","DESCRICAO":"PREMIUM SEMIBRILHO 18L ERVA DOCE"},{"CODPROD":"3232","DESCRICAO":"PREMIUM SEMIBRILHO 18L VERDE MENTA"},{"CODPROD":"3233","DESCRICAO":"PREMIUM SEMIBRILHO 18L AMAZONITA"},{"CODPROD":"3234","DESCRICAO":"PREMIUM SEMIBRILHO 18L JADE"},{"CODPROD":"3235","DESCRICAO":"PREMIUM SEMIBRILHO 18L BRANCO SIRIEMA"},{"CODPROD":"3237","DESCRICAO":"PREMIUM SEMIBRILHO 18L SANHACU"},{"CODPROD":"3239","DESCRICAO":"PREMIUM SEMIBRILHO 18L ANOITECER"},{"CODPROD":"3240","DESCRICAO":"PREMIUM SEMIBRILHO 18L AZUL PROFUNDO"},{"CODPROD":"3241","DESCRICAO":"PREMIUM SEMIBRILHO 18L FERVEDOURO"},{"CODPROD":"3242","DESCRICAO":"PREMIUM SEMIBRILHO 18L TURMALINA AZUL"},{"CODPROD":"3243","DESCRICAO":"PREMIUM SEMIBRILHO 18L AZUL BEIJA FLOR"},{"CODPROD":"3244","DESCRICAO":"PREMIUM SEMIBRILHO 18L VITORIA REGIA"},{"CODPROD":"3245","DESCRICAO":"PREMIUM SEMIBRILHO 18L BOTO ROSA"},{"CODPROD":"3246","DESCRICAO":"PREMIUM SEMIBRILHO 18L COPAIBA"},{"CODPROD":"3247","DESCRICAO":"PREMIUM SEMIBRILHO 18L IPE ROSA"},{"CODPROD":"3249","DESCRICAO":"PREMIUM SEMIBRILHO 18L BROMELIA"},{"CODPROD":"3256","DESCRICAO":"TEXTURA RISCADA 25KG BARBANTE"},{"CODPROD":"3258","DESCRICAO":"TEXTURA RISCADA 25KG LUA CHEIA"},{"CODPROD":"3259","DESCRICAO":"TEXTURA RISCADA 25KG AREIA"},{"CODPROD":"3261","DESCRICAO":"TEXTURA RISCADA 25KG JENIPAPO"},{"CODPROD":"3263","DESCRICAO":"TEXTURA RISCADA 25KG BEGE FAVORITO"},{"CODPROD":"3264","DESCRICAO":"TEXTURA RISCADA 25KG ANDIROBA"},{"CODPROD":"3265","DESCRICAO":"TEXTURA RISCADA 25KG CASTANHEIRA"},{"CODPROD":"3266","DESCRICAO":"TEXTURA RISCADA 25KG CASCALHO DE RIO"},{"CODPROD":"3267","DESCRICAO":"TEXTURA RISCADA 25KG CHOCOLATE"},{"CODPROD":"3268","DESCRICAO":"TEXTURA RISCADA 25KG CARCARA"},{"CODPROD":"3269","DESCRICAO":"TEXTURA RISCADA 25KG SANHACU"},{"CODPROD":"3270","DESCRICAO":"TEXTURA RISCADA 25KG ANOITECER"},{"CODPROD":"3271","DESCRICAO":"TEXTURA RISCADA 25KG MARSALLA"},{"CODPROD":"3272","DESCRICAO":"TEXTURA RISCADA 25KG NEVOA"},{"CODPROD":"3273","DESCRICAO":"TEXTURA RISCADA 25KG CINZA AVELUDA"},{"CODPROD":"3274","DESCRICAO":"TEXTURA RISCADA 25KG CONCRETO"},{"CODPROD":"3275","DESCRICAO":"TEXTURA RISCADA 25KG VERDE MENTA"},{"CODPROD":"3277","DESCRICAO":"TEXTURA RISCADA 25KG JADE"},{"CODPROD":"3279","DESCRICAO":"TEXTURA RISCADA 25KG VERDE LIMAO"},{"CODPROD":"3280","DESCRICAO":"TEXTURA RISCADA 25KG VERDE MUSGO"},{"CODPROD":"3282","DESCRICAO":"TEXTURA RISCADA 25KG CINZA TAUPE"},{"CODPROD":"3285","DESCRICAO":"TEXTURA RISCADA 25KG CINZA PRATEADO"},{"CODPROD":"3287","DESCRICAO":"TEXTURA RISCADA 25KG AZUL SERENO"},{"CODPROD":"3288","DESCRICAO":"TEXTURA RISCADA 25KG TITANIO"},{"CODPROD":"3304","DESCRICAO":"TEXTURA TRADICIONAL 25KG TITANIO"},{"CODPROD":"3306","DESCRICAO":"TEXTURA TRADICIONAL 25KG AZUL SERENO"},{"CODPROD":"3308","DESCRICAO":"TEXTURA TRADICIONAL 25KG CINZA PRATEADO"},{"CODPROD":"3311","DESCRICAO":"TEXTURA TRADICIONAL 25KG CINZA TAUPE"},{"CODPROD":"3313","DESCRICAO":"TEXTURA TRADICIONAL 25KG VERDE MUSGO"},{"CODPROD":"3316","DESCRICAO":"TEXTURA TRADICIONAL 25KG VERDE LIMAO"},{"CODPROD":"3317","DESCRICAO":"TEXTURA TRADICIONAL 25KG JADE"},{"CODPROD":"3319","DESCRICAO":"TEXTURA TRADICIONAL 25KG VERDE MENTA"},{"CODPROD":"3322","DESCRICAO":"TEXTURA TRADICIONAL 25KG CINZA AVELUDADO"},{"CODPROD":"3324","DESCRICAO":"TEXTURA TRADICIONAL 25KG NEVOA"},{"CODPROD":"3326","DESCRICAO":"TEXTURA TRADICIONAL 25KG MARSALLA"},{"CODPROD":"3330","DESCRICAO":"TEXTURA TRADICIONAL 25KG ANOITECER"},{"CODPROD":"3331","DESCRICAO":"TEXTURA TRADICIONAL 25KG SANHACU"},{"CODPROD":"3332","DESCRICAO":"TEXTURA TRADICIONAL 25KG CARCARA"},{"CODPROD":"3333","DESCRICAO":"TEXTURA TRADICIONAL 25KG CASCALHO DE RIO"},{"CODPROD":"3334","DESCRICAO":"TEXTURA TRADICIONAL 25KG CASTANHEIRA"},{"CODPROD":"3335","DESCRICAO":"TEXTURA TRADICIONAL 25KG ANDIROBA"},{"CODPROD":"3336","DESCRICAO":"TEXTURA TRADICIONAL 25KG BEGE FAVORITO"},{"CODPROD":"3337","DESCRICAO":"TEXTURA TRADICIONAL 25KG JENIPAPO"},{"CODPROD":"3338","DESCRICAO":"TEXTURA TRADICIONAL 25KG LUA CHEIA"},{"CODPROD":"3339","DESCRICAO":"TEXTURA TRADICIONAL 25KG BARBANTE"},{"CODPROD":"3340","DESCRICAO":"PREMIUM ACET SEDA 18L ARAPONGA"},{"CODPROD":"3341","DESCRICAO":"PREMIUM ACET SEDA 18L BARBANTE"},{"CODPROD":"3342","DESCRICAO":"PREMIUM ACET SEDA 18L BEGE FAVORITO"},{"CODPROD":"3343","DESCRICAO":"PREMIUM ACET SEDA 18L BRANCO SIRIEMA"},{"CODPROD":"3344","DESCRICAO":"PREMIUM ACET SEDA 18L ROSA CHA"},{"CODPROD":"3345","DESCRICAO":"PREMIUM SEMIBRILHO 3,6L SEIXO BRANCO"},{"CODPROD":"3346","DESCRICAO":"PREMIUM SEMIBRILHO 3,6L CINZA PRATEADO"},{"CODPROD":"3347","DESCRICAO":"PREMIUM SEMIBRILHO 3,6L AZUL SERENO"},{"CODPROD":"3348","DESCRICAO":"PREMIUM SEMIBRILHO 3,6L ARAPONGA"},{"CODPROD":"3349","DESCRICAO":"PREMIUM SEMIBRILHO 3,6L NEVOA"},{"CODPROD":"3350","DESCRICAO":"PREMIUM SEMIBRILHO 3,6L CINZA AVELUDADO"},{"CODPROD":"3351","DESCRICAO":"PREMIUM SEMIBRILHO 3,6L MARSALLA"},{"CODPROD":"3352","DESCRICAO":"PREMIUM SEMIBRILHO 3,6L CINZA TAUPE"},{"CODPROD":"3353","DESCRICAO":"PREMIUM SEMIBRILHO 3,6L TITANIO"},{"CODPROD":"3354","DESCRICAO":"PREMIUM SEMIBRILHO 3,6L PRETO"},{"CODPROD":"3355","DESCRICAO":"PREMIUM SEMIBRILHO 3,6L ROSA CHA"},{"CODPROD":"3356","DESCRICAO":"PREMIUM SEMIBRILHO 3,6L BARBANTE"},{"CODPROD":"3357","DESCRICAO":"PREMIUM SEMIBRILHO 3,6L LUA CHEIA"},{"CODPROD":"3358","DESCRICAO":"PREMIUM SEMIBRILHO 3,6L BEGE FAVORITO"},{"CODPROD":"3359","DESCRICAO":"PREMIUM SEMIBRILHO 3,6L ANDIROBA"},{"CODPROD":"3360","DESCRICAO":"PREMIUM SEMIBRILHO 3,6L CASTANHEIRA"},{"CODPROD":"3361","DESCRICAO":"PREMIUM SEMIBRILHO 3,6L CASCALHO DE RIO"},{"CODPROD":"3362","DESCRICAO":"PREMIUM SEMIBRILHO 3,6L CARCAR"},{"CODPROD":"3363","DESCRICAO":"PREMIUM SEMIBRILHO 3,6L JENIPAPO"},{"CODPROD":"3364","DESCRICAO":"PREMIUM SEMIBRILHO 3,6L AMARELO SOL"},{"CODPROD":"3365","DESCRICAO":"PREMIUM SEMIBRILHO 3,6L CERAMICA"},{"CODPROD":"3366","DESCRICAO":"PREMIUM SEMIBRILHO 3,6L VERDE MENTA"},{"CODPROD":"3367","DESCRICAO":"PREMIUM SEMIBRILHO 3,6L CARDEAL"},{"CODPROD":"3368","DESCRICAO":"PREMIUM SEMIBRILHO 3,6L AMAZONITA"},{"CODPROD":"3369","DESCRICAO":"PREMIUM SEMIBRILHO 3,6L JADE"},{"CODPROD":"3370","DESCRICAO":"PREMIUM SEMIBRILHO 3,6L BRANCO SIRIEMA"},{"CODPROD":"3371","DESCRICAO":"PREMIUM SEMIBRILHO 3,6L SANHACU"},{"CODPROD":"3372","DESCRICAO":"PREMIUM SEMIBRILHO 3,6L ANOITECER"},{"CODPROD":"3373","DESCRICAO":"PREMIUM SEMIBRILHO 3,6L AZUL PROFUNDO"},{"CODPROD":"3374","DESCRICAO":"PREMIUM SEMIBRILHO 3,6L FERVEDOURO"},{"CODPROD":"3375","DESCRICAO":"PREMIUM SEMIBRILHO 3,6L TURMALINA AZUL"},{"CODPROD":"3376","DESCRICAO":"PREMIUM SEMIBRILHO 3,6L AZUL BEIJA FLOR"},{"CODPROD":"3377","DESCRICAO":"PREMIUM SEMIBRILHO 3,6L VITORIA REGIA"},{"CODPROD":"3378","DESCRICAO":"PREMIUM SEMIBRILHO 3,6L BOTO ROSA"},{"CODPROD":"3379","DESCRICAO":"PREMIUM SEMIBRILHO 3,6L COPAIBA"},{"CODPROD":"3380","DESCRICAO":"PREMIUM SEMIBRILHO 3,6L IPE ROSA"},{"CODPROD":"3381","DESCRICAO":"PREMIUM SEMIBRILHO 3,6L BROMELIA"},{"CODPROD":"3388","DESCRICAO":"STANDARD SB 18L AZUL PROFUNDO"},{"CODPROD":"3390","DESCRICAO":"STANDARD SB 3,6L AZUL PROFUNDO"},{"CODPROD":"3391","DESCRICAO":"STANDARD FS 3,6L AZUL PROFUNDO"},{"CODPROD":"3392","DESCRICAO":"TINTA ACRILICA ESPECIAL"},{"CODPROD":"3394","DESCRICAO":"TEXTURA TRADICIONAL 20KG AREIA"},{"CODPROD":"3395","DESCRICAO":"TEXTURA TRADICIONAL 20KG BRANCO GELO"},{"CODPROD":"3396","DESCRICAO":"TEXTURA TRADICIONAL 20KG CAMURCA"},{"CODPROD":"3397","DESCRICAO":"TEXTURA TRADICIONAL 20KG PALHA"},{"CODPROD":"3398","DESCRICAO":"TEXTURA TRADICIONAL 20KG BRANCO NATURAL"},{"CODPROD":"3399","DESCRICAO":"TEXTURA TRADICIONAL 20KG BARBANTE"},{"CODPROD":"3400","DESCRICAO":"TEXTURA TRADICIONAL 20KG LUA CHEIA"},{"CODPROD":"3401","DESCRICAO":"TEXTURA TRADICIONAL 20KG JENIPAPO"},{"CODPROD":"3402","DESCRICAO":"TEXTURA TRADICIONAL 20KG BEGE FAVORITO"},{"CODPROD":"3403","DESCRICAO":"TEXTURA TRADICIONAL 20KG ANDIROBA"},{"CODPROD":"3404","DESCRICAO":"TEXTURA TRADICIONAL 20KG CASTANHEIRA"},{"CODPROD":"3405","DESCRICAO":"TEXTURA TRADICIONAL 20KG CASCALHO DE RIO"},{"CODPROD":"3406","DESCRICAO":"TEXTURA TRADICIONAL 20KG CHOCOLATE"},{"CODPROD":"3407","DESCRICAO":"TEXTURA TRADICIONAL 20KG CARCARA"},{"CODPROD":"3408","DESCRICAO":"TEXTURA TRADICIONAL 20KG SANHACU"},{"CODPROD":"3409","DESCRICAO":"TEXTURA TRADICIONAL 20KG ANOITECER"},{"CODPROD":"3410","DESCRICAO":"TEXTURA TRADICIONAL 20KG MARSALLA"},{"CODPROD":"3411","DESCRICAO":"TEXTURA TRADICIONAL 20KG NEVOA"},{"CODPROD":"3412","DESCRICAO":"TEXTURA TRADICIONAL 20KG CINZA AVELUDA"},{"CODPROD":"3413","DESCRICAO":"TEXTURA TRADICIONAL 20KG CONCRETO"},{"CODPROD":"3414","DESCRICAO":"TEXTURA TRADICIONAL 20KG VERDE MENTA"},{"CODPROD":"3415","DESCRICAO":"TEXTURA TRADICIONAL 20KG JADE"},{"CODPROD":"3416","DESCRICAO":"TEXTURA TRADICIONAL 20KG VERDE LIMAO"},{"CODPROD":"3417","DESCRICAO":"TEXTURA TRADICIONAL 20KG VERDE MUSGO"},{"CODPROD":"3418","DESCRICAO":"TEXTURA TRADICIONAL 20KG CINZA TAUPE"},{"CODPROD":"3419","DESCRICAO":"TEXTURA TRADICIONAL 20KG CINZA PRATEADO"},{"CODPROD":"3420","DESCRICAO":"TEXTURA TRADICIONAL 20KG AZUL SERENO"},{"CODPROD":"3421","DESCRICAO":"TEXTURA TRADICIONAL 20KG TITANIO"},{"CODPROD":"3422","DESCRICAO":"TEXTURA RISCADA 20KG AREIA"},{"CODPROD":"3423","DESCRICAO":"TEXTURA RISCADA 20KG BRANCO GELO"},{"CODPROD":"3424","DESCRICAO":"TEXTURA RISCADA 20KG CAMURCA"},{"CODPROD":"3425","DESCRICAO":"TEXTURA RISCADA 20KG PALHA"},{"CODPROD":"3426","DESCRICAO":"TEXTURA RISCADA 20KG BARBANTE"},{"CODPROD":"3427","DESCRICAO":"TEXTURA RISCADA 20KG BRANCO NATURAL"},{"CODPROD":"3428","DESCRICAO":"TEXTURA RISCADA 20KG LUA CHEIA"},{"CODPROD":"3429","DESCRICAO":"TEXTURA RISCADA 20KG JENIPAPO"},{"CODPROD":"3430","DESCRICAO":"TEXTURA RISCADA 20KG BEGE FAVORITO"},{"CODPROD":"3431","DESCRICAO":"TEXTURA RISCADA 20KG ANDIROBA"},{"CODPROD":"3432","DESCRICAO":"TEXTURA RISCADA 20KG CASTANHEIRA"},{"CODPROD":"3433","DESCRICAO":"TEXTURA RISCADA 20KG CASCALHO DE RIO"},{"CODPROD":"3434","DESCRICAO":"TEXTURA RISCADA 20KG CHOCOLATE"},{"CODPROD":"3435","DESCRICAO":"TEXTURA RISCADA 20KG CARCARA"},{"CODPROD":"3436","DESCRICAO":"TEXTURA RISCADA 20KG SANHACU"},{"CODPROD":"3437","DESCRICAO":"TEXTURA RISCADA 20KG ANOITECER"},{"CODPROD":"3438","DESCRICAO":"TEXTURA RISCADA 20KG MARSALLA"},{"CODPROD":"3439","DESCRICAO":"TEXTURA RISCADA 20KG NEVOA"},{"CODPROD":"3440","DESCRICAO":"TEXTURA RISCADA 20KG CINZA AVELUDA"},{"CODPROD":"3441","DESCRICAO":"TEXTURA RISCADA 20KG CONCRETO "},{"CODPROD":"3442","DESCRICAO":"TEXTURA RISCADA 20KG VERDE MENTA"},{"CODPROD":"3443","DESCRICAO":"TEXTURA RISCADA 20KG JADE"},{"CODPROD":"3444","DESCRICAO":"TEXTURA RISCADA 20KG VERDE LIMAO"},{"CODPROD":"3445","DESCRICAO":"TEXTURA RISCADA 20KG VERDE MUSGO"},{"CODPROD":"3446","DESCRICAO":"TEXTURA RISCADA 20KG CINZA TAUPE"},{"CODPROD":"3447","DESCRICAO":"TEXTURA RISCADA 20KG CINZA PRATEADO"},{"CODPROD":"3448","DESCRICAO":"TEXTURA RISCADA 20KG AZUL SERENO"},{"CODPROD":"3449","DESCRICAO":"TEXTURA RISCADA 20KG TITANIO"},{"CODPROD":"3450","DESCRICAO":"ECONOMICO FOSCO 18L VERDE ESPERANCA"},{"CODPROD":"3451","DESCRICAO":"ECONOMICO FOSCO 3,6L VERDE ESPERANCA"},{"CODPROD":"3452","DESCRICAO":"PREMIUM SEMIBRILHO 3,6L ERVA DOCE"},{"CODPROD":"3453","DESCRICAO":"STANDARD SB 18L BEGE FAVORITO"},{"CODPROD":"3454","DESCRICAO":"STANDARD SB 18L CONCRETO"},{"CODPROD":"3457","DESCRICAO":"FUNDO SERRALHEIRO 0,9L VERMELHO OXIDO"},{"CODPROD":"3518","DESCRICAO":"STANDARD FS 18L ILHA DO TESOURO"},{"CODPROD":"3519","DESCRICAO":"STANDARD FS 3,6L ILHA DO TESOURO"},{"CODPROD":"3521","DESCRICAO":"STANDARD SB 18L ILHA DO TESOURO"},{"CODPROD":"3527","DESCRICAO":"TEXTURA TRADICIONAL 20KG CAFE COM LEITE"},{"CODPROD":"3538","DESCRICAO":"TEXTURA TRADICIONAL 20KG CAPUCCINO "},{"CODPROD":"3550","DESCRICAO":"ESMALTE SINT BRILHANTE 3,6L ILHA TESOURO"},{"CODPROD":"3568","DESCRICAO":"TEXTURA TRADICIONAL 15KG PRATA ENVELHECI"},{"CODPROD":"3585","DESCRICAO":"ESMALTE SINT ACETINADO 0,9L BRANCO NEVE"},{"CODPROD":"3586","DESCRICAO":"ESMALTE SINT ACETINADO 0,9L BRANCO GELO"},{"CODPROD":"3587","DESCRICAO":"ESMALTE SINT ACETINADO 3,6L BRANCO NEVE"},{"CODPROD":"3588","DESCRICAO":"ESMALTE SINT ACETINADO 3,6L BRANCO GELO"},{"CODPROD":"3595","DESCRICAO":"STANDARD FS 18L OLIVA SILVESTRE"},{"CODPROD":"3596","DESCRICAO":"STANDARD FS 3,6L OLIVA SILVESTRE"},{"CODPROD":"3597","DESCRICAO":"ESMALTE SINT BRILHANTE 18L PRETO"},{"CODPROD":"3599","DESCRICAO":"TEXTURA TRAD 15KG CARVAO ANTRACITE"},{"CODPROD":"3601","DESCRICAO":"TEXTURA TRADICIONAL 15KG NEVOA"},{"CODPROD":"3610","DESCRICAO":"PISO PREMIUM FS 18L VERDE LISO"},{"CODPROD":"3611","DESCRICAO":"PISO PREMIUM FS 3,6L VERDE LISO"},{"CODPROD":"3616","DESCRICAO":"TEXTURA RISCADA 15KG NEVOA"},{"CODPROD":"3618","DESCRICAO":"TEXTURA TRADICIONAL 25KG AZUL ARARA"},{"CODPROD":"3619","DESCRICAO":"TEXTURA TRADICIONAL 20KG AZUL ARARA"},{"CODPROD":"3620","DESCRICAO":"TEXTURA TRADICIONAL 15KG AZUL ARARA"},{"CODPROD":"3621","DESCRICAO":"FUNDO SINTETICO 18L CINZA MEDIO"},{"CODPROD":"3622","DESCRICAO":"FUNDO E ACABAMENTO 200L AZUL ROYAL"},{"CODPROD":"3623","DESCRICAO":"ESMALTE SINT BRILHANTE 0,9L CINZA PLACA"},{"CODPROD":"3624","DESCRICAO":"ESMALTE SINT BRILHANTE 3,6L CINZA PLACA"},{"CODPROD":"3625","DESCRICAO":"ESMALTE SINT BRILHANTE 18L CINZA PLACA"},{"CODPROD":"3630","DESCRICAO":"TEXTURA TRADICIONAL 15KG LONDRES"},{"CODPROD":"3633","DESCRICAO":"TEXTURA TRADICIONAL 15KG VIENA"},{"CODPROD":"3638","DESCRICAO":"STANDARD SB 18L GREENWAY AP164-4"},{"CODPROD":"3639","DESCRICAO":"STANDARD SB 18L GRASS CUT AP65-5"},{"CODPROD":"3640","DESCRICAO":"STANDARD SB 3,6L GREENWAY AP164-4"},{"CODPROD":"3641","DESCRICAO":"STANDARD SB 3,6L GRASS CUT AP65-5"},{"CODPROD":"3649","DESCRICAO":"TEXTURA RISCADA 15KG MRV2013-09"},{"CODPROD":"3661","DESCRICAO":"FIT ACR FS ECONOMICO 14L BRANCO NEVE "},{"CODPROD":"3662","DESCRICAO":"FIT ACR FS ECONOMICO 14L BRANCO GELO"},{"CODPROD":"3663","DESCRICAO":"FIT ACR FS ECONOMICO 14L AMARELO CANARIO"},{"CODPROD":"3664","DESCRICAO":"FIT ACR FS ECONOMICO 14L AMAZONITA"},{"CODPROD":"3665","DESCRICAO":"FIT ACR FS ECONOMICO 14L ARAPONGA"},{"CODPROD":"3666","DESCRICAO":"FIT ACR FS ECONOMICO 14L AREIA"},{"CODPROD":"3667","DESCRICAO":"FIT ACR FS ECONOMICO 14L LILAS"},{"CODPROD":"3668","DESCRICAO":"FIT ACR FS ECONOMICO 14L MARFIM"},{"CODPROD":"3669","DESCRICAO":"FIT ACR FS ECONOMICO 14L PALHA"},{"CODPROD":"3670","DESCRICAO":"FIT ACR FS ECONOMICO 14L PEROLA"},{"CODPROD":"3671","DESCRICAO":"FIT ACR FS ECONOMICO 14L SANHACU"},{"CODPROD":"3672","DESCRICAO":"FIT FUNDO PREPARADOR DE PAREDES 14L"},{"CODPROD":"3673","DESCRICAO":"FIT MASSA ACRILICA 23 KG"},{"CODPROD":"3674","DESCRICAO":"FIT MASSA CORRIDA PVA 23 KG"},{"CODPROD":"3675","DESCRICAO":"FIT SELADOR ACRILICO KOKAR 14L"},{"CODPROD":"3687","DESCRICAO":"TEXTURA TRADICIONAL 15KG CINZA AVELUDADO"},{"CODPROD":"3690","DESCRICAO":"STANDARD FS 18L VERDE QUARTEL"},{"CODPROD":"3691","DESCRICAO":"STANDARD FS 3,6L VERDE QUARTEL"},{"CODPROD":"3695","DESCRICAO":"ESMALTE SINT BR 18L VERDE CORP HEINEKEN"},{"CODPROD":"3715","DESCRICAO":"TEXTURA TRADICIONAL 25KG TROFEU DE PRATA"},{"CODPROD":"3723","DESCRICAO":"TEXTURA TRADICIONAL 25KG ELEFANTE D161"},{"CODPROD":"3727","DESCRICAO":"GRANULADO LUME 25KG ALGODAO EGIPICIO"},{"CODPROD":"3732","DESCRICAO":"TEXTURA TRADICIONAL 25KG BURITI"},{"CODPROD":"3735","DESCRICAO":"FIT ACR FS ECONOMICO 16L MAR DE GELO"},{"CODPROD":"3737","DESCRICAO":"STANDARD FS 18L SISAL"},{"CODPROD":"3744","DESCRICAO":"ECONOMICO FOSCO 18L DOCE MARROM"},{"CODPROD":"3749","DESCRICAO":"ECONOMICO FOSCO 18L CALDA DE CHOCOLATE"},{"CODPROD":"3752","DESCRICAO":"TEXTURA TRADICIONAL 20KG COOL GRAY"},{"CODPROD":"3757","DESCRICAO":"TEXTURA RISCADA 20KG MINERIO DE FERRO"},{"CODPROD":"3759","DESCRICAO":"TEXTURA RISCADA 20KG GOLFINHO DE NORONHA"},{"CODPROD":"3764","DESCRICAO":"TEXTURA RISCADA 20KG CINZA NEVOA"},{"CODPROD":"3766","DESCRICAO":"GRANULADO LUME 25KG JENIPAPO"},{"CODPROD":"3769","DESCRICAO":"GRANULADO LUME 25KG MINERIO BRUTO"},{"CODPROD":"3770","DESCRICAO":"TEXTURA RISCADA 20KG CASA DE PEDRA"},{"CODPROD":"3774","DESCRICAO":"TEXTURA TRADICIONAL 20KG CARMUCA NOBRE"},{"CODPROD":"3776","DESCRICAO":"STANDARD FS ULTRA 3,6L NEVOA"},{"CODPROD":"3782","DESCRICAO":"PISO PREMIUM ACET 18L BRANCO"},{"CODPROD":"3783","DESCRICAO":"PISO PREMIUM ACET 18L AZUL"},{"CODPROD":"3784","DESCRICAO":"PISO PREMIUM ACET 18L CINZA"},{"CODPROD":"3785","DESCRICAO":"PISO PREMIUM ACET 18L CINZA ESCURO"},{"CODPROD":"3786","DESCRICAO":"PISO PREMIUM ACET 18L CONCRETO"},{"CODPROD":"3787","DESCRICAO":"PISO PREMIUM ACET 18L VERDE"},{"CODPROD":"3788","DESCRICAO":"PISO PREMIUM ACET 3,6L AZUL"},{"CODPROD":"3789","DESCRICAO":"PISO PREMIUM ACET 3,6L BRANCO"},{"CODPROD":"3790","DESCRICAO":"PISO PREMIUM ACET 3,6L CINZA"},{"CODPROD":"3791","DESCRICAO":"PISO PREMIUM ACET 3,6L CINZA ESCURO"},{"CODPROD":"3792","DESCRICAO":"PISO PREMIUM ACET 3,6L CONCRETO"},{"CODPROD":"3793","DESCRICAO":"PISO PREMIUM ACET 3,6L VERDE"},{"CODPROD":"3809","DESCRICAO":"DURAFER FUNDO E ACAB 18L AMA CATERPILA"},{"CODPROD":"3810","DESCRICAO":"DURAFER FUNDO E ACAB 18L AMARELO OURO"},{"CODPROD":"3811","DESCRICAO":"DURAFER FUNDO E ACAB 18L BRANCO"},{"CODPROD":"3812","DESCRICAO":"DURAFER FUNDO E ACAB 18L AMA SEGURANCA"},{"CODPROD":"3813","DESCRICAO":"DURAFER FUNDO E ACAB 18L AZUL DEL REY"},{"CODPROD":"3814","DESCRICAO":"DURAFER FUNDO E ACAB 18L AZUL FRANCA"},{"CODPROD":"3815","DESCRICAO":"DURAFER FUNDO E ACAB 18L CINZA MEDIO"},{"CODPROD":"3816","DESCRICAO":"DURAFER FUNDO E ACAB 18L GRAFITE"},{"CODPROD":"3817","DESCRICAO":"DURAFER FUNDO E ACAB 18L LARANJA"},{"CODPROD":"3818","DESCRICAO":"DURAFER FUNDO E ACAB 18L PLATINA"},{"CODPROD":"3819","DESCRICAO":"DURAFER FUNDO E ACAB 18L PRETO"},{"CODPROD":"3820","DESCRICAO":"DURAFER FUNDO E ACAB 18L VERDE FOLHA"},{"CODPROD":"3821","DESCRICAO":"DURAFER FUNDO E ACAB 18L VERMELHO OXIDO"},{"CODPROD":"3822","DESCRICAO":"DURAFER FUNDO E ACAB 3,6L AMA CATERPILAR"},{"CODPROD":"3823","DESCRICAO":"DURAFER FUNDO E ACAB 3,6L AMARELO OURO"},{"CODPROD":"3824","DESCRICAO":"DURAFER FUNDO E ACAB 3,6L AMA SEGURANCA"},{"CODPROD":"3825","DESCRICAO":"DURAFER FUNDO E ACAB 3,6L AZUL DEL REY"},{"CODPROD":"3826","DESCRICAO":"DURAFER FUNDO E ACAB 3,6L AZUL FRANCA"},{"CODPROD":"3827","DESCRICAO":"DURAFER FUNDO E ACAB 3,6L BRANCO"},{"CODPROD":"3828","DESCRICAO":"DURAFER FUNDO E ACAB 3,6L CINZA MEDIO"},{"CODPROD":"3829","DESCRICAO":"DURAFER FUNDO E ACAB 3,6L GRAFITE"},{"CODPROD":"3830","DESCRICAO":"DURAFER FUNDO E ACAB 3,6L LARANJA"},{"CODPROD":"3831","DESCRICAO":"DURAFER FUNDO E ACAB 3,6L PLATINA"},{"CODPROD":"3832","DESCRICAO":"DURAFER FUNDO E ACAB 3,6L PRETO"},{"CODPROD":"3833","DESCRICAO":"DURAFER FUNDO E ACAB 3,6L VERDE FOLHA"},{"CODPROD":"3834","DESCRICAO":"DURAFER FUNDO E ACAB 3,6L VERMELHO OXIDO"},{"CODPROD":"3835","DESCRICAO":"ESMALTE SINT BRILHANTE 0,9L VERDE LAB 01"},{"CODPROD":"3836","DESCRICAO":"ESMALTE SINT BRILHANTE 3,6L VERDE LAB 01"},{"CODPROD":"3855","DESCRICAO":"ESM SINT AUTO BR 3,6L ALUMINIO"},{"CODPROD":"3856","DESCRICAO":"ESM SINT AUTO BR 3,6L AMARELO CATERPILAR"},{"CODPROD":"3857","DESCRICAO":"ESM SINT AUTO BR 3,6L AMARELO SEGURANCA"},{"CODPROD":"3858","DESCRICAO":"ESM SINT AUTO BR 3,6L AZUL DEL REY"},{"CODPROD":"3859","DESCRICAO":"ESM SINT AUTO BR 3,6L AZUL FRANCA"},{"CODPROD":"3860","DESCRICAO":"ESM SINT AUTO BR 3,6L BRANCO"},{"CODPROD":"3861","DESCRICAO":"ESM SINT AUTO BR 3,6L CINZA N6,5"},{"CODPROD":"3862","DESCRICAO":"ESM SINT AUTO BR 3,6L CINZA PLACA"},{"CODPROD":"3863","DESCRICAO":"ESM SINT AUTO BR 3,6L PRETO CADILAC"},{"CODPROD":"3864","DESCRICAO":"ESM SINT AUTO 3,6L PRETO FOSCO"},{"CODPROD":"3865","DESCRICAO":"ESM SINT AUTO BR 3,6L VERDE JOHN DEERE"},{"CODPROD":"3866","DESCRICAO":"ESM SINT AUTO BR 3,6L VERMELHO SEGURANCA"},{"CODPROD":"3876","DESCRICAO":"KOKAR 123 IMPERM 16L ANDIROBA"},{"CODPROD":"3877","DESCRICAO":"KOKAR 123 IMPERM 16L ARAPONGA"},{"CODPROD":"3878","DESCRICAO":"KOKAR 123 IMPERM 16L AREIA"},{"CODPROD":"3879","DESCRICAO":"KOKAR 123 IMPERM 16L BRANCO"},{"CODPROD":"3880","DESCRICAO":"KOKAR 123 IMPERM 16L BRANCO GELO"},{"CODPROD":"3881","DESCRICAO":"KOKAR 123 IMPERM 16L CAMURCA"},{"CODPROD":"3882","DESCRICAO":"KOKAR 123 IMPERM 16L CINZA PRATEADO"},{"CODPROD":"3883","DESCRICAO":"KOKAR 123 IMPERM 16L MARFIM"},{"CODPROD":"3884","DESCRICAO":"KOKAR 123 IMPERM 16L PALHA"},{"CODPROD":"3888","DESCRICAO":"ESM SINT AUTO BR 0,9L ALUMINIO"},{"CODPROD":"3889","DESCRICAO":"ESM SINT AUTO BR 0,9L AMARELO CATERPILAR"},{"CODPROD":"3890","DESCRICAO":"ESM SINT AUTO BR 0,9L AMARELO SEGURANCA"},{"CODPROD":"3891","DESCRICAO":"ESM SINT AUTO BR 0,9L AZUL DEL REY"},{"CODPROD":"3892","DESCRICAO":"ESM SINT AUTO BR 0,9L AZUL FRANCA"},{"CODPROD":"3893","DESCRICAO":"ESM SINT AUTO BR 0,9L BRANCO"},{"CODPROD":"3894","DESCRICAO":"ESM SINT AUTO BR 0,9L CINZA N6,5"},{"CODPROD":"3895","DESCRICAO":"ESM SINT AUTO BR 0,9L CINZA PLACA"},{"CODPROD":"3896","DESCRICAO":"ESM SINT AUTO BR 0,9L PRETO CADILAC"},{"CODPROD":"3897","DESCRICAO":"ESM SINT AUTO BR 0,9L VERDE JOHN DEERE"},{"CODPROD":"3898","DESCRICAO":"ESM SINT AUTO BR 0,9L VERMELHO SEGURANCA"},{"CODPROD":"3899","DESCRICAO":"ESM SINT AUTO 0,9L PRETO FOSCO"},{"CODPROD":"3901","DESCRICAO":"RESINA BASE SOLVENTE 18L INCOLOR"},{"CODPROD":"3902","DESCRICAO":"RESINA BASE SOLVENTE 5L INCOLOR"},{"CODPROD":"3904","DESCRICAO":"SILICONE HIDROFUGANTE KOKAR 18L"},{"CODPROD":"3905","DESCRICAO":"SILICONE HIDROFUGANTE KOKAR 5L"},{"CODPROD":"3907","DESCRICAO":"BORRACHA LIQUIDA KOKAR 18L BRANCO BASE"},{"CODPROD":"3908","DESCRICAO":"KOKARFLEX MANTA LIQUIDA 16KG"},{"CODPROD":"3911","DESCRICAO":"STANDARD ACETINADO 18L BRANCO NEVE"},{"CODPROD":"3912","DESCRICAO":"STANDARD ACETINADO 18L BRANCO GELO"},{"CODPROD":"3913","DESCRICAO":"STANDARD ACETINADO 3,6L BRANCO NEVE"},{"CODPROD":"3914","DESCRICAO":"STANDARD ACETINADO 3,6L BRANCO GELO"},{"CODPROD":"3921","DESCRICAO":"REV CIMENTO QUEIMADO 4,8KG ELEFANTE D161"}]